Workbook
Name SegmentaçãodeDados_DATA: #N/A

Sheet SEPARAÇÃO
A1: NF | B1: PV | C1: SEPARADOR | D1: DATA | E1: SKU'S | F1: TR ou NC | G1: STATUS PRODUÇÃO | H1: STATUS | I1: VOLUMES | J1: PALETES | K1: SEPARAÇÃO ($) | L1: CLIENTE | M1: OCORRÊNCIAS CLIENTES | N1: SETOR RESPONSÁVEL | O1: DADOS TRANSPORTE | P1: SOLICITANTE URGÊNCIAS | Q1: MOTIVOS
A2: =IFERROR(INDEX(NFS!F:F,MATCH(B2,NFS!E:E,0)),"") -> 179000 | B2: 69312 | C2: MIJOHNSON | D2: 46304 | E2: =IF(B2="","",COUNTIF(SKU!C:C,B2)) -> 38 | F2: CARRO PROPRIO | G2: FATURADO | H2: BACKLOG | I2: =IF(A2="","",IFERROR(VLOOKUP(TEXT(A2,"0"),#REF!,9,FALSE),"")) | K2: =IFERROR(INDEX(#REF!,MATCH(A2,#REF!,0)),"") | L2: =IFERROR(INDEX(SKU!E:E,MATCH(B2,SKU!C:C,0)),"") -> ACALANTO CLINICA | R2: =IF(COUNTIF(ROMANEIOS!K:K,A2)>0,J2,"")
A3: =IFERROR(INDEX(NFS!F:F,MATCH(B3,NFS!E:E,0)),"") -> 178891 | B3: 66744 | C3: WELINGTON | D3: 46303 | E3: =IF(B3="","",COUNTIF(SKU!C:C,B3)) -> 3 | F3: CARRO PROPRIO | G3: FATURADO | H3: BACKLOG | I3: =IF(A3="","",IFERROR(VLOOKUP(TEXT(A3,"0"),#REF!,9,FALSE),"")) | K3: =IFERROR(INDEX(#REF!,MATCH(A3,#REF!,0)),"") | L3: =IFERROR(INDEX(SKU!E:E,MATCH(B3,SKU!C:C,0)),"") -> ALBERT EINSTEIN | R3: =IF(COUNTIF(ROMANEIOS!K:K,A3)>0,J3,"")
A4: =IFERROR(INDEX(NFS!F:F,MATCH(B4,NFS!E:E,0)),"") -> 178846 | B4: 69219 | C4: RAONI | D4: 46302 | E4: =IF(B4="","",COUNTIF(SKU!C:C,B4)) -> 2 | F4: CARRO PROPRIO | G4: FATURADO | H4: SAUDAVEL | L4: =IFERROR(INDEX(SKU!E:E,MATCH(B4,SKU!C:C,0)),"") -> DASA ALTA EXCELENCIA | R4: =IF(COUNTIF(ROMANEIOS!K:K,A4)>0,J4,"")
A5: =IFERROR(INDEX(NFS!F:F,MATCH(B5,NFS!E:E,0)),"") -> 178927 | B5: 66745 | C5: WELINGTON | D5: 46303 | E5: =IF(B5="","",COUNTIF(SKU!C:C,B5)) -> 2 | F5: CARRO PROPRIO | G5: FATURADO | H5: BACKLOG | I5: =IF(A5="","",IFERROR(VLOOKUP(TEXT(A5,"0"),#REF!,9,FALSE),"")) | K5: =IFERROR(INDEX(#REF!,MATCH(A5,#REF!,0)),"") | L5: =IFERROR(INDEX(SKU!E:E,MATCH(B5,SKU!C:C,0)),"") -> ALBERT EINSTEIN | R5: =IF(COUNTIF(ROMANEIOS!K:K,A5)>0,J5,"")
A6: =IFERROR(INDEX(NFS!F:F,MATCH(B6,NFS!E:E,0)),"") -> 178831 | B6: 69552 | C6: RAONI | D6: 46302 | E6: =IF(B6="","",COUNTIF(SKU!C:C,B6)) -> 1 | F6: CARRO PROPRIO | G6: FATURADO | H6: SAUDAVEL | L6: =IFERROR(INDEX(SKU!E:E,MATCH(B6,SKU!C:C,0)),"") -> DASA PQ DUQUE CAXIAS | R6: =IF(COUNTIF(ROMANEIOS!K:K,A6)>0,J6,"")
A7: =IFERROR(INDEX(NFS!F:F,MATCH(B7,NFS!E:E,0)),"") -> 178956 | B7: 65062 | C7: WELINGTON | D7: 46303 | E7: =IF(B7="","",COUNTIF(SKU!C:C,B7)) -> 3 | F7: CARRO PROPRIO | G7: FATURADO | H7: BACKLOG | I7: =IF(A7="","",IFERROR(VLOOKUP(TEXT(A7,"0"),#REF!,9,FALSE),"")) | K7: =IFERROR(INDEX(#REF!,MATCH(A7,#REF!,0)),"") | L7: =IFERROR(INDEX(SKU!E:E,MATCH(B7,SKU!C:C,0)),"") -> ALBERT EINSTEIN | R7: =IF(COUNTIF(ROMANEIOS!K:K,A7)>0,J7,"")
A8: =IFERROR(INDEX(NFS!F:F,MATCH(B8,NFS!E:E,0)),"") -> 178856 | B8: 69261 | C8: CLAUDIO | D8: 46302 | E8: =IF(B8="","",COUNTIF(SKU!C:C,B8)) -> 5 | F8: CARRO PROPRIO | G8: FATURADO | H8: SAUDAVEL | L8: =IFERROR(INDEX(SKU!E:E,MATCH(B8,SKU!C:C,0)),"") -> MASTER HIGIMED RJ | R8: =IF(COUNTIF(ROMANEIOS!K:K,A8)>0,J8,"")
A9: =IFERROR(INDEX(NFS!F:F,MATCH(B9,NFS!E:E,0)),"") -> 178833 | B9: 68875 | C9: PAIVA | D9: 46302 | E9: =IF(B9="","",COUNTIF(SKU!C:C,B9)) -> 1 | F9: CARRO PROPRIO | G9: FATURADO | H9: SAUDAVEL | L9: =IFERROR(INDEX(SKU!E:E,MATCH(B9,SKU!C:C,0)),"") -> DASA PQ DUQUE CAXIAS | R9: =IF(COUNTIF(ROMANEIOS!K:K,A9)>0,J9,"")
A10: =IFERROR(INDEX(NFS!F:F,MATCH(B10,NFS!E:E,0)),"") -> 178832 | B10: 69385 | C10: PAIVA | D10: 46302 | E10: =IF(B10="","",COUNTIF(SKU!C:C,B10)) -> 6 | F10: CARRO PROPRIO | G10: FATURADO | H10: SAUDAVEL | L10: =IFERROR(INDEX(SKU!E:E,MATCH(B10,SKU!C:C,0)),"") -> DASA PQ DUQUE CAXIAS | R10: =IF(COUNTIF(ROMANEIOS!K:K,A10)>0,J10,"")
A11: =IFERROR(INDEX(NFS!F:F,MATCH(B11,NFS!E:E,0)),"") -> 178864 | B11: 68993 | C11: JOÃO PAULO | D11: 46302 | E11: =IF(B11="","",COUNTIF(SKU!C:C,B11)) -> 44 | F11: CARRO PROPRIO | G11: FATURADO | H11: SAUDAVEL | L11: =IFERROR(INDEX(SKU!E:E,MATCH(B11,SKU!C:C,0)),"") -> DASA PQ DUQUE CAXIAS | R11: =IF(COUNTIF(ROMANEIOS!K:K,A11)>0,J11,"")
A12: =IFERROR(INDEX(NFS!F:F,MATCH(B12,NFS!E:E,0)),"") -> 178854 | B12: 69475 | C12: RAPHAEL | D12: 46302 | E12: =IF(B12="","",COUNTIF(SKU!C:C,B12)) -> 11 | F12: CARRO PROPRIO | G12: FATURADO | H12: SAUDAVEL | L12: =IFERROR(INDEX(SKU!E:E,MATCH(B12,SKU!C:C,0)),"") -> DASA DIAGNOSTICO | R12: =IF(COUNTIF(ROMANEIOS!K:K,A12)>0,J12,"")
A13: =IFERROR(INDEX(NFS!F:F,MATCH(B13,NFS!E:E,0)),"") -> 178890 | B13: 66736 | C13: WELINGTON | D13: 46303 | E13: =IF(B13="","",COUNTIF(SKU!C:C,B13)) -> 1 | F13: CARRO PROPRIO | G13: FATURADO | H13: BACKLOG | I13: =IF(A13="","",IFERROR(VLOOKUP(TEXT(A13,"0"),#REF!,9,FALSE),"")) | K13: =IFERROR(INDEX(#REF!,MATCH(A13,#REF!,0)),"") | L13: =IFERROR(INDEX(SKU!E:E,MATCH(B13,SKU!C:C,0)),"") -> ALBERT EINSTEIN | R13: =IF(COUNTIF(ROMANEIOS!K:K,A13)>0,J13,"")
A14: =IFERROR(INDEX(NFS!F:F,MATCH(B14,NFS!E:E,0)),"") -> 178837 | B14: 69154 | C14: RAONI | D14: 46302 | E14: =IF(B14="","",COUNTIF(SKU!C:C,B14)) -> 1 | F14: CARRO PROPRIO | G14: FATURADO | H14: SAUDAVEL | L14: =IFERROR(INDEX(SKU!E:E,MATCH(B14,SKU!C:C,0)),"") -> ALBERT EINSTEIN | R14: =IF(COUNTIF(ROMANEIOS!K:K,A14)>0,J14,"")
A15: =IFERROR(INDEX(NFS!F:F,MATCH(B15,NFS!E:E,0)),"") -> 178834 | B15: 69365 | C15: RAONI | D15: 46302 | E15: =IF(B15="","",COUNTIF(SKU!C:C,B15)) -> 5 | F15: CARRO PROPRIO | G15: FATURADO | H15: SAUDAVEL | L15: =IFERROR(INDEX(SKU!E:E,MATCH(B15,SKU!C:C,0)),"") -> DASA S JOSE PINHAIS | R15: =IF(COUNTIF(ROMANEIOS!K:K,A15)>0,J15,"")
A16: =IFERROR(INDEX(NFS!F:F,MATCH(B16,NFS!E:E,0)),"") -> 178835 | B16: 69345 | C16: RAONI | D16: 46302 | E16: =IF(B16="","",COUNTIF(SKU!C:C,B16)) -> 9 | F16: CARRO PROPRIO | G16: FATURADO | H16: SAUDAVEL | L16: =IFERROR(INDEX(SKU!E:E,MATCH(B16,SKU!C:C,0)),"") -> DASA CASCAVEL | R16: =IF(COUNTIF(ROMANEIOS!K:K,A16)>0,J16,"")
A17: =IFERROR(INDEX(NFS!F:F,MATCH(B17,NFS!E:E,0)),"") -> 178814 | B17: 69671 | C17: MTC | D17: 46302 | E17: =IF(B17="","",COUNTIF(SKU!C:C,B17)) -> 1 | F17: CARRO PROPRIO | G17: FATURADO | H17: SAUDAVEL | L17: =IFERROR(INDEX(SKU!E:E,MATCH(B17,SKU!C:C,0)),"") -> HAPVIDA | R17: =IF(COUNTIF(ROMANEIOS!K:K,A17)>0,J17,"")
A18: =IFERROR(INDEX(NFS!F:F,MATCH(B18,NFS!E:E,0)),"") -> 178838 | B18: 69386 | C18: MAURICIO | D18: 46302 | E18: =IF(B18="","",COUNTIF(SKU!C:C,B18)) -> 4 | F18: CARRO PROPRIO | G18: FATURADO | H18: SAUDAVEL | L18: =IFERROR(INDEX(SKU!E:E,MATCH(B18,SKU!C:C,0)),"") -> DASA PQ DUQUE CAXIAS | R18: =IF(COUNTIF(ROMANEIOS!K:K,A18)>0,J18,"")
A19: =IFERROR(INDEX(NFS!F:F,MATCH(B19,NFS!E:E,0)),"") -> 178851 | B19: 69424 | C19: MAURICIO | D19: 46302 | E19: =IF(B19="","",COUNTIF(SKU!C:C,B19)) -> 5 | F19: CARRO PROPRIO | G19: FATURADO | H19: SAUDAVEL | I19: =IF(A19="","",IFERROR(VLOOKUP(TEXT(A19,"0"),#REF!,9,FALSE),"")) | K19: =IFERROR(INDEX(#REF!,MATCH(A19,#REF!,0)),"") | L19: =IFERROR(INDEX(SKU!E:E,MATCH(B19,SKU!C:C,0)),"") -> ALBERT EINSTEIN | R19: =IF(COUNTIF(ROMANEIOS!K:K,A19)>0,J19,"")
A20: =IFERROR(INDEX(NFS!F:F,MATCH(B20,NFS!E:E,0)),"") -> 178866 | B20: 69426 | C20: LEANDRO | D20: 46302 | E20: =IF(B20="","",COUNTIF(SKU!C:C,B20)) -> 6 | F20: CARRO PROPRIO | G20: FATURADO | H20: SAUDAVEL | I20: =IF(A20="","",IFERROR(VLOOKUP(TEXT(A20,"0"),#REF!,9,FALSE),"")) | K20: =IFERROR(INDEX(#REF!,MATCH(A20,#REF!,0)),"") | L20: =IFERROR(INDEX(SKU!E:E,MATCH(B20,SKU!C:C,0)),"") -> ALBERT EINSTEIN | R20: =IF(COUNTIF(ROMANEIOS!K:K,A20)>0,J20,"")
A21: =IFERROR(INDEX(NFS!F:F,MATCH(B21,NFS!E:E,0)),"") -> 178865 | B21: 69427 | C21: LEANDRO | D21: 46302 | E21: =IF(B21="","",COUNTIF(SKU!C:C,B21)) -> 5 | F21: CARRO PROPRIO | G21: FATURADO | H21: SAUDAVEL | I21: =IF(A21="","",IFERROR(VLOOKUP(TEXT(A21,"0"),#REF!,9,FALSE),"")) | K21: =IFERROR(INDEX(#REF!,MATCH(A21,#REF!,0)),"") | L21: =IFERROR(INDEX(SKU!E:E,MATCH(B21,SKU!C:C,0)),"") -> ALBERT EINSTEIN | R21: =IF(COUNTIF(ROMANEIOS!K:K,A21)>0,J21,"")
A22: =IFERROR(INDEX(NFS!F:F,MATCH(B22,NFS!E:E,0)),"") -> 178953 | B22: 68904 | C22: RAONI | D22: 46303 | E22: =IF(B22="","",COUNTIF(SKU!C:C,B22)) -> 1 | F22: CARRO PROPRIO | G22: FATURADO | H22: BACKLOG | I22: =IF(A22="","",IFERROR(VLOOKUP(TEXT(A22,"0"),#REF!,9,FALSE),"")) | K22: =IFERROR(INDEX(#REF!,MATCH(A22,#REF!,0)),"") | L22: =IFERROR(INDEX(SKU!E:E,MATCH(B22,SKU!C:C,0)),"") -> ALBERT EINSTEIN | R22: =IF(COUNTIF(ROMANEIOS!K:K,A22)>0,J22,"")
A23: =IFERROR(INDEX(NFS!F:F,MATCH(B23,NFS!E:E,0)),"") -> 178952 | B23: 68737 | C23: RAONI | D23: 46303 | E23: =IF(B23="","",COUNTIF(SKU!C:C,B23)) -> 2 | F23: CARRO PROPRIO | G23: FATURADO | H23: BACKLOG | I23: =IF(A23="","",IFERROR(VLOOKUP(TEXT(A23,"0"),#REF!,9,FALSE),"")) | K23: =IFERROR(INDEX(#REF!,MATCH(A23,#REF!,0)),"") | L23: =IFERROR(INDEX(SKU!E:E,MATCH(B23,SKU!C:C,0)),"") -> ALBERT EINSTEIN | R23: =IF(COUNTIF(ROMANEIOS!K:K,A23)>0,J23,"")
A24: =IFERROR(INDEX(NFS!F:F,MATCH(B24,NFS!E:E,0)),"") -> 178962 | B24: 68749 | C24: RAONI | D24: 46303 | E24: =IF(B24="","",COUNTIF(SKU!C:C,B24)) -> 1 | F24: CARRO PROPRIO | G24: FATURADO | H24: BACKLOG | I24: =IF(A24="","",IFERROR(VLOOKUP(TEXT(A24,"0"),#REF!,9,FALSE),"")) | K24: =IFERROR(INDEX(#REF!,MATCH(A24,#REF!,0)),"") | L24: =IFERROR(INDEX(SKU!E:E,MATCH(B24,SKU!C:C,0)),"") -> ALBERT EINSTEIN | R24: =IF(COUNTIF(ROMANEIOS!K:K,A24)>0,J24,"")
A25: =IFERROR(INDEX(NFS!F:F,MATCH(B25,NFS!E:E,0)),"") -> 178961 | B25: 68736 | C25: RAONI | D25: 46303 | E25: =IF(B25="","",COUNTIF(SKU!C:C,B25)) -> 1 | F25: CARRO PROPRIO | G25: FATURADO | H25: BACKLOG | I25: =IF(A25="","",IFERROR(VLOOKUP(TEXT(A25,"0"),#REF!,9,FALSE),"")) | K25: =IFERROR(INDEX(#REF!,MATCH(A25,#REF!,0)),"") | L25: =IFERROR(INDEX(SKU!E:E,MATCH(B25,SKU!C:C,0)),"") -> ALBERT EINSTEIN | R25: =IF(COUNTIF(ROMANEIOS!K:K,A25)>0,J25,"")
A26: =IFERROR(INDEX(NFS!F:F,MATCH(B26,NFS!E:E,0)),"") -> 178857 | B26: 69794 | C26: RAONI | D26: 46302 | E26: 1 | F26: CARRO PROPRIO | G26: FATURADO | H26: SAUDAVEL | I26: =IF(A26="","",IFERROR(VLOOKUP(TEXT(A26,"0"),#REF!,9,FALSE),"")) | K26: =IFERROR(INDEX(#REF!,MATCH(A26,#REF!,0)),"") | L26: REAL E BENEMERITA | R26: =IF(COUNTIF(ROMANEIOS!K:K,A26)>0,J26,"")
A27: =IFERROR(INDEX(NFS!F:F,MATCH(B27,NFS!E:E,0)),"") -> 179018 | B27: 69093 | C27: IVAN | D27: 46304 | E27: =IF(B27="","",COUNTIF(SKU!C:C,B27)) -> 1 | F27: CARRO PROPRIO | G27: FATURADO | H27: BACKLOG | I27: =IF(A27="","",IFERROR(VLOOKUP(TEXT(A27,"0"),#REF!,9,FALSE),"")) | K27: =IFERROR(INDEX(#REF!,MATCH(A27,#REF!,0)),"") | L27: =IFERROR(INDEX(SKU!E:E,MATCH(B27,SKU!C:C,0)),"") -> ALBERT EINSTEIN | R27: =IF(COUNTIF(ROMANEIOS!K:K,A27)>0,J27,"")
A28: =IFERROR(INDEX(NFS!F:F,MATCH(B28,NFS!E:E,0)),"") -> 178858 | B28: 69699 | C28: MATHEUS | D28: 46302 | E28: 1 | F28: CARRO PROPRIO | G28: FATURADO | H28: SAUDAVEL | I28: =IF(A28="","",IFERROR(VLOOKUP(TEXT(A28,"0"),#REF!,9,FALSE),"")) | K28: =IFERROR(INDEX(#REF!,MATCH(A28,#REF!,0)),"") | L28: DIAGNOSTICOS DA AMERICA SA | R28: =IF(COUNTIF(ROMANEIOS!K:K,A28)>0,J28,"")
A29: =IFERROR(INDEX(NFS!F:F,MATCH(B29,NFS!E:E,0)),"") -> 178998 | B29: 69352 | C29: WELINGTON | D29: 46304 | E29: =IF(B29="","",COUNTIF(SKU!C:C,B29)) -> 2 | F29: CARRO PROPRIO | G29: FATURADO | H29: BACKLOG | I29: =IF(A29="","",IFERROR(VLOOKUP(TEXT(A29,"0"),#REF!,9,FALSE),"")) | K29: =IFERROR(INDEX(#REF!,MATCH(A29,#REF!,0)),"") | L29: =IFERROR(INDEX(SKU!E:E,MATCH(B29,SKU!C:C,0)),"") -> ALBERT EINSTEIN | R29: =IF(COUNTIF(ROMANEIOS!K:K,A29)>0,J29,"")
A30: =IFERROR(INDEX(NFS!F:F,MATCH(B30,NFS!E:E,0)),"") -> 178999 | B30: 69149 | C30: WELINGTON | D30: 46304 | E30: =IF(B30="","",COUNTIF(SKU!C:C,B30)) -> 1 | F30: CARRO PROPRIO | G30: FATURADO | H30: BACKLOG | I30: =IF(A30="","",IFERROR(VLOOKUP(TEXT(A30,"0"),#REF!,9,FALSE),"")) | K30: =IFERROR(INDEX(#REF!,MATCH(A30,#REF!,0)),"") | L30: =IFERROR(INDEX(SKU!E:E,MATCH(B30,SKU!C:C,0)),"") -> ALBERT EINSTEIN | R30: =IF(COUNTIF(ROMANEIOS!K:K,A30)>0,J30,"")
A31: =IFERROR(INDEX(NFS!F:F,MATCH(B31,NFS!E:E,0)),"") -> 178869 | B31: 69464 | C31: LEANDRO | D31: 46302 | E31: =IF(B31="","",COUNTIF(SKU!C:C,B31)) -> 2 | F31: BROS | G31: FATURADO | H31: SAUDAVEL | I31: =IF(A31="","",IFERROR(VLOOKUP(TEXT(A31,"0"),#REF!,9,FALSE),"")) | K31: =IFERROR(INDEX(#REF!,MATCH(A31,#REF!,0)),"") | L31: =IFERROR(INDEX(SKU!E:E,MATCH(B31,SKU!C:C,0)),"") -> DASA CUIABA | R31: =IF(COUNTIF(ROMANEIOS!K:K,A31)>0,J31,"")
A32: =IFERROR(INDEX(NFS!F:F,MATCH(B32,NFS!E:E,0)),"") -> 179015 | B32: 69351 | C32: WELINGTON | D32: 46304 | E32: =IF(B32="","",COUNTIF(SKU!C:C,B32)) -> 7 | F32: CARRO PROPRIO | G32: FATURADO | H32: BACKLOG | I32: =IF(A32="","",IFERROR(VLOOKUP(TEXT(A32,"0"),#REF!,9,FALSE),"")) | K32: =IFERROR(INDEX(#REF!,MATCH(A32,#REF!,0)),"") | L32: =IFERROR(INDEX(SKU!E:E,MATCH(B32,SKU!C:C,0)),"") -> ALBERT EINSTEIN | R32: =IF(COUNTIF(ROMANEIOS!K:K,A32)>0,J32,"")
A33: =IFERROR(INDEX(NFS!F:F,MATCH(B33,NFS!E:E,0)),"") -> 179039 | B33: 69437 | C33: WELINGTON | D33: 46304 | E33: =IF(B33="","",COUNTIF(SKU!C:C,B33)) -> 7 | F33: CARRO PROPRIO | G33: FATURADO | H33: BACKLOG | I33: =IF(A33="","",IFERROR(VLOOKUP(TEXT(A33,"0"),#REF!,9,FALSE),"")) | K33: =IFERROR(INDEX(#REF!,MATCH(A33,#REF!,0)),"") | L33: =IFERROR(INDEX(SKU!E:E,MATCH(B33,SKU!C:C,0)),"") -> ALBERT EINSTEIN | R33: =IF(COUNTIF(ROMANEIOS!K:K,A33)>0,J33,"")
A34: =IFERROR(INDEX(NFS!F:F,MATCH(B34,NFS!E:E,0)),"") -> 178880 | B34: 69016 | C34: SANDRO | D34: 46303 | E34: 1 | F34: CARRO PROPRIO | G34: FATURADO | H34: SAUDAVEL | I34: =IF(A34="","",IFERROR(VLOOKUP(TEXT(A34,"0"),#REF!,9,FALSE),"")) | K34: =IFERROR(INDEX(#REF!,MATCH(A34,#REF!,0)),"") | L34: SOCIEDADE BENEF ISRAELITABRAS HOSP ALBER | R34: =IF(COUNTIF(ROMANEIOS!K:K,A34)>0,J34,"")
A35: =IFERROR(INDEX(NFS!F:F,MATCH(B35,NFS!E:E,0)),"") -> 178943 | B35: 69324 | C35: SANDRO | D35: 46303 | E35: =IF(B35="","",COUNTIF(SKU!C:C,B35)) -> 5 | F35: BTA | G35: FATURADO | H35: SAUDAVEL | I35: =IF(A35="","",IFERROR(VLOOKUP(TEXT(A35,"0"),#REF!,9,FALSE),"")) | K35: =IFERROR(INDEX(#REF!,MATCH(A35,#REF!,0)),"") | L35: =IFERROR(INDEX(SKU!E:E,MATCH(B35,SKU!C:C,0)),"") -> DASA GOIANIA | R35: =IF(COUNTIF(ROMANEIOS!K:K,A35)>0,J35,"")
A36: =IFERROR(INDEX(NFS!F:F,MATCH(B36,NFS!E:E,0)),"") | B36: 69215 | C36: JOÃO PAULO | D36: 46303 | E36: 1 | F36: CARRO PROPRIO | G36: CONFERIDO | H36: SAUDAVEL | I36: =IF(A36="","",IFERROR(VLOOKUP(TEXT(A36,"0"),#REF!,9,FALSE),"")) | K36: =IFERROR(INDEX(#REF!,MATCH(A36,#REF!,0)),"") | L36: SOCIEDADE BENEF ISRAELITABRAS HOSP ALBER | R36: =IF(COUNTIF(ROMANEIOS!K:K,A36)>0,J36,"") -> 0
A37: =IFERROR(INDEX(NFS!F:F,MATCH(B37,NFS!E:E,0)),"") -> 178872 | B37: 69195 | C37: JOÃO PAULO | D37: 46303 | E37: =IF(B37="","",COUNTIF(SKU!C:C,B37)) -> 1 | F37: CARRO PROPRIO | G37: FATURADO | H37: SAUDAVEL | I37: =IF(A37="","",IFERROR(VLOOKUP(TEXT(A37,"0"),#REF!,9,FALSE),"")) | K37: =IFERROR(INDEX(#REF!,MATCH(A37,#REF!,0)),"") | L37: =IFERROR(INDEX(SKU!E:E,MATCH(B37,SKU!C:C,0)),"") -> SIRIO LIBANES | R37: =IF(COUNTIF(ROMANEIOS!K:K,A37)>0,J37,"")
A38: =IFERROR(INDEX(NFS!F:F,MATCH(B38,NFS!E:E,0)),"") -> 178874 | B38: 69194 | C38: JOÃO PAULO | D38: 46303 | E38: =IF(B38="","",COUNTIF(SKU!C:C,B38)) -> 2 | F38: CARRO PROPRIO | G38: FATURADO | H38: SAUDAVEL | I38: =IF(A38="","",IFERROR(VLOOKUP(TEXT(A38,"0"),#REF!,9,FALSE),"")) | K38: =IFERROR(INDEX(#REF!,MATCH(A38,#REF!,0)),"") | L38: =IFERROR(INDEX(SKU!E:E,MATCH(B38,SKU!C:C,0)),"") -> SIRIO LIBANES | R38: =IF(COUNTIF(ROMANEIOS!K:K,A38)>0,J38,"")
A39: =IFERROR(INDEX(NFS!F:F,MATCH(B39,NFS!E:E,0)),"") -> 178968 | B39: 69040 | C39: JOÃO PAULO | D39: 46303 | E39: =IF(B39="","",COUNTIF(SKU!C:C,B39)) -> 3 | F39: CARRO PROPRIO | G39: FATURADO | H39: SAUDAVEL | I39: =IF(A39="","",IFERROR(VLOOKUP(TEXT(A39,"0"),#REF!,9,FALSE),"")) | K39: =IFERROR(INDEX(#REF!,MATCH(A39,#REF!,0)),"") | L39: =IFERROR(INDEX(SKU!E:E,MATCH(B39,SKU!C:C,0)),"") -> ALBERT EINSTEIN | R39: =IF(COUNTIF(ROMANEIOS!K:K,A39)>0,J39,"")
A40: =IFERROR(INDEX(NFS!F:F,MATCH(B40,NFS!E:E,0)),"") | B40: 68942 | C40: JOÃO PAULO | D40: 46303 | E40: =IF(B40="","",COUNTIF(SKU!C:C,B40)) -> 1 | F40: CARRO PROPRIO | G40: SEPARANDO | H40: SAUDAVEL | I40: =IF(A40="","",IFERROR(VLOOKUP(TEXT(A40,"0"),#REF!,9,FALSE),"")) | K40: =IFERROR(INDEX(#REF!,MATCH(A40,#REF!,0)),"") | L40: =IFERROR(INDEX(SKU!E:E,MATCH(B40,SKU!C:C,0)),"") -> HOSP INFANTIL SABARA | R40: =IF(COUNTIF(ROMANEIOS!K:K,A40)>0,J40,"") -> 0
A41: =IFERROR(INDEX(NFS!F:F,MATCH(B41,NFS!E:E,0)),"") -> 178967 | B41: 69329 | C41: PAIVA | D41: 46303 | E41: =IF(B41="","",COUNTIF(SKU!C:C,B41)) -> 5 | F41: BTA | G41: FATURADO | H41: SAUDAVEL | I41: =IF(A41="","",IFERROR(VLOOKUP(TEXT(A41,"0"),#REF!,9,FALSE),"")) | K41: =IFERROR(INDEX(#REF!,MATCH(A41,#REF!,0)),"") | L41: =IFERROR(INDEX(SKU!E:E,MATCH(B41,SKU!C:C,0)),"") -> LUSTOSA | R41: =IF(COUNTIF(ROMANEIOS!K:K,A41)>0,J41,"")
A42: =IFERROR(INDEX(NFS!F:F,MATCH(B42,NFS!E:E,0)),"") -> 178886 | B42: 69326 | C42: PAIVA | D42: 46303 | E42: =IF(B42="","",COUNTIF(SKU!C:C,B42)) -> 6 | F42: ARLETE | G42: FATURADO | H42: SAUDAVEL | I42: =IF(A42="","",IFERROR(VLOOKUP(TEXT(A42,"0"),#REF!,9,FALSE),"")) | K42: =IFERROR(INDEX(#REF!,MATCH(A42,#REF!,0)),"") | L42: =IFERROR(INDEX(SKU!E:E,MATCH(B42,SKU!C:C,0)),"") -> MARINGA MED NUCLEAR | R42: =IF(COUNTIF(ROMANEIOS!K:K,A42)>0,J42,"")
A43: =IFERROR(INDEX(NFS!F:F,MATCH(B43,NFS!E:E,0)),"") -> 178978 | B43: 69569 | C43: MAURICIO | D43: 46303 | E43: =IF(B43="","",COUNTIF(SKU!C:C,B43)) -> 35 | F43: CARRO PROPRIO | G43: FATURADO | H43: BACKLOG | I43: =IF(A43="","",IFERROR(VLOOKUP(TEXT(A43,"0"),#REF!,9,FALSE),"")) | K43: =IFERROR(INDEX(#REF!,MATCH(A43,#REF!,0)),"") | L43: =IFERROR(INDEX(SKU!E:E,MATCH(B43,SKU!C:C,0)),"") -> ALTANA BORGES LAGOA | R43: =IF(COUNTIF(ROMANEIOS!K:K,A43)>0,J43,"")
A44: =IFERROR(INDEX(NFS!F:F,MATCH(B44,NFS!E:E,0)),"") | B44: 68859 | C44: RAPHAEL | D44: 46303 | E44: =IF(B44="","",COUNTIF(SKU!C:C,B44)) -> 9 | F44: PACIFICO | G44: SEPARANDO | H44: SAUDAVEL | I44: =IF(A44="","",IFERROR(VLOOKUP(TEXT(A44,"0"),#REF!,9,FALSE),"")) | J44: =IF(A44="","",VALUE(IFERROR(VLOOKUP(TEXT(A44,"0"),#REF!,10,FALSE),0))) | K44: =IFERROR(INDEX(#REF!,MATCH(A44,#REF!,0)),"") | L44: =IFERROR(INDEX(SKU!E:E,MATCH(B44,SKU!C:C,0)),"") -> DASA RECIFE 61.486.6 | R44: =IF(COUNTIF(ROMANEIOS!K:K,A44)>0,J44,"")
A45: =IFERROR(INDEX(NFS!F:F,MATCH(B45,NFS!E:E,0)),"") -> 178885 | B45: 69306 | C45: RAPHAEL | D45: 46303 | E45: =IF(B45="","",COUNTIF(SKU!C:C,B45)) -> 9 | F45: PACIFICO | G45: FATURADO | H45: SAUDAVEL | I45: =IF(A45="","",IFERROR(VLOOKUP(TEXT(A45,"0"),#REF!,9,FALSE),"")) | K45: =IFERROR(INDEX(#REF!,MATCH(A45,#REF!,0)),"") | L45: =IFERROR(INDEX(SKU!E:E,MATCH(B45,SKU!C:C,0)),"") -> DASA RECIFE 61.486.6 | R45: =IF(COUNTIF(ROMANEIOS!K:K,A45)>0,J45,"")
A46: =IFERROR(INDEX(NFS!F:F,MATCH(B46,NFS!E:E,0)),"") -> 178940 | B46: 69605 | C46: KARINA | D46: 46303 | E46: =IF(B46="","",COUNTIF(SKU!C:C,B46)) -> 1 | F46: RISSO | G46: FATURADO | H46: SAUDAVEL | I46: =IF(A46="","",IFERROR(VLOOKUP(TEXT(A46,"0"),#REF!,9,FALSE),"")) | K46: =IFERROR(INDEX(#REF!,MATCH(A46,#REF!,0)),"") | L46: =IFERROR(INDEX(SKU!E:E,MATCH(B46,SKU!C:C,0)),"") -> HYDRO | R46: =IF(COUNTIF(ROMANEIOS!K:K,A46)>0,J46,"")
A47: =IFERROR(INDEX(NFS!F:F,MATCH(B47,NFS!E:E,0)),"") -> 178950 | B47: 69619 | C47: KARINA | D47: 46303 | E47: =IF(B47="","",COUNTIF(SKU!C:C,B47)) -> 1 | F47: CARRO PROPRIO | G47: FATURADO | H47: SAUDAVEL | I47: =IF(A47="","",IFERROR(VLOOKUP(TEXT(A47,"0"),#REF!,9,FALSE),"")) | K47: =IFERROR(INDEX(#REF!,MATCH(A47,#REF!,0)),"") | L47: =IFERROR(INDEX(SKU!E:E,MATCH(B47,SKU!C:C,0)),"") -> ALBERT EINSTEIN | R47: =IF(COUNTIF(ROMANEIOS!K:K,A47)>0,J47,"")
A48: =IFERROR(INDEX(NFS!F:F,MATCH(B48,NFS!E:E,0)),"") -> 178951 | B48: 69654 | C48: KARINA | D48: 46303 | E48: =IF(B48="","",COUNTIF(SKU!C:C,B48)) -> 1 | F48: CARRO PROPRIO | G48: FATURADO | H48: SAUDAVEL | I48: =IF(A48="","",IFERROR(VLOOKUP(TEXT(A48,"0"),#REF!,9,FALSE),"")) | K48: =IFERROR(INDEX(#REF!,MATCH(A48,#REF!,0)),"") | L48: =IFERROR(INDEX(SKU!E:E,MATCH(B48,SKU!C:C,0)),"") -> FRATELLI 25.258.705/ | R48: =IF(COUNTIF(ROMANEIOS!K:K,A48)>0,J48,"")
A49: =IFERROR(INDEX(NFS!F:F,MATCH(B49,NFS!E:E,0)),"") -> 178949 | B49: 69657 | C49: KARINA | D49: 46303 | E49: =IF(B49="","",COUNTIF(SKU!C:C,B49)) -> 1 | F49: CARRO PROPRIO | G49: FATURADO | H49: SAUDAVEL | I49: =IF(A49="","",IFERROR(VLOOKUP(TEXT(A49,"0"),#REF!,9,FALSE),"")) | K49: =IFERROR(INDEX(#REF!,MATCH(A49,#REF!,0)),"") | L49: =IFERROR(INDEX(SKU!E:E,MATCH(B49,SKU!C:C,0)),"") -> EUCATEX | R49: =IF(COUNTIF(ROMANEIOS!K:K,A49)>0,J49,"")
A50: =IFERROR(INDEX(NFS!F:F,MATCH(B50,NFS!E:E,0)),"") -> 178931 | B50: 69680 | C50: KARINA | D50: 46303 | E50: =IF(B50="","",COUNTIF(SKU!C:C,B50)) -> 1 | F50: CARRO PROPRIO | G50: FATURADO | H50: SAUDAVEL | I50: =IF(A50="","",IFERROR(VLOOKUP(TEXT(A50,"0"),#REF!,9,FALSE),"")) | K50: =IFERROR(INDEX(#REF!,MATCH(A50,#REF!,0)),"") | L50: =IFERROR(INDEX(SKU!E:E,MATCH(B50,SKU!C:C,0)),"") -> HOSPITAL BANDEIRANTE | R50: =IF(COUNTIF(ROMANEIOS!K:K,A50)>0,J50,"")
A51: =IFERROR(INDEX(NFS!F:F,MATCH(B51,NFS!E:E,0)),"") -> 179361 | B51: 69706 | C51: MIJOHNSON | D51: 46308 | E51: =IF(B51="","",COUNTIF(SKU!C:C,B51)) -> 2 | F51: CARRO PROPRIO | G51: SEPARANDO | H51: SAUDAVEL | I51: =IF(A51="","",IFERROR(VLOOKUP(TEXT(A51,"0"),#REF!,9,FALSE),"")) | K51: =IFERROR(INDEX(#REF!,MATCH(A51,#REF!,0)),"") | L51: =IFERROR(INDEX(SKU!E:E,MATCH(B51,SKU!C:C,0)),"") -> HAPVIDA | R51: =IF(COUNTIF(ROMANEIOS!K:K,A51)>0,J51,"")
A52: =IFERROR(INDEX(NFS!F:F,MATCH(B52,NFS!E:E,0)),"") | B52: 69715 | C52: MAURICIO | D52: 46311 | E52: 1 | F52: CARRO PROPRIO | G52: SEPARANDO | H52: SAUDAVEL | I52: =IF(A52="","",IFERROR(VLOOKUP(TEXT(A52,"0"),#REF!,9,FALSE),"")) | K52: =IFERROR(INDEX(#REF!,MATCH(A52,#REF!,0)),"") | L52: NOTRE DAME INTERMEDICA SAUDE SA | R52: =IF(COUNTIF(ROMANEIOS!K:K,A52)>0,J52,"") -> 0
A53: =IFERROR(INDEX(NFS!F:F,MATCH(B53,NFS!E:E,0)),"") -> 178932 | B53: 69719 | C53: KARINA | D53: 46303 | E53: =IF(B53="","",COUNTIF(SKU!C:C,B53)) -> 1 | F53: CARRO PROPRIO | G53: FATURADO | H53: SAUDAVEL | I53: =IF(A53="","",IFERROR(VLOOKUP(TEXT(A53,"0"),#REF!,9,FALSE),"")) | K53: =IFERROR(INDEX(#REF!,MATCH(A53,#REF!,0)),"") | L53: =IFERROR(INDEX(SKU!E:E,MATCH(B53,SKU!C:C,0)),"") -> HOSPITAL AC CAMARGO | R53: =IF(COUNTIF(ROMANEIOS!K:K,A53)>0,J53,"")
A54: =IFERROR(INDEX(NFS!F:F,MATCH(B54,NFS!E:E,0)),"") -> 178871 | B54: 69685 | C54: ANDRE SOUZA | D54: 46303 | E54: =IF(B54="","",COUNTIF(SKU!C:C,B54)) -> 3 | F54: RISSO | G54: FATURADO | H54: SAUDAVEL | I54: =IF(A54="","",IFERROR(VLOOKUP(TEXT(A54,"0"),#REF!,9,FALSE),"")) | K54: =IFERROR(INDEX(#REF!,MATCH(A54,#REF!,0)),"") | L54: =IFERROR(INDEX(SKU!E:E,MATCH(B54,SKU!C:C,0)),"") -> SANTA CASA DE MOGI | R54: =IF(COUNTIF(ROMANEIOS!K:K,A54)>0,J54,"")
A55: =IFERROR(INDEX(NFS!F:F,MATCH(B55,NFS!E:E,0)),"") -> 178997 | B55: 69356 | C55: RAPHAEL | D55: 46304 | E55: =IF(B55="","",COUNTIF(SKU!C:C,B55)) -> 33 | F55: CARRO PROPRIO | G55: FATURADO | H55: BACKLOG | I55: =IF(A55="","",IFERROR(VLOOKUP(TEXT(A55,"0"),#REF!,9,FALSE),"")) | K55: =IFERROR(INDEX(#REF!,MATCH(A55,#REF!,0)),"") | L55: =IFERROR(INDEX(SKU!E:E,MATCH(B55,SKU!C:C,0)),"") -> ALTANA TATUAPÃ‰ | R55: =IF(COUNTIF(ROMANEIOS!K:K,A55)>0,J55,"")
A56: =IFERROR(INDEX(NFS!F:F,MATCH(B56,NFS!E:E,0)),"") -> 178829 | B56: 69065 | C56: MARCOS | D56: 46302 | E56: =IF(B56="","",COUNTIF(SKU!C:C,B56)) -> 6 | F56: CARRO PROPRIO | G56: FATURADO | H56: BACKLOG | L56: =IFERROR(INDEX(SKU!E:E,MATCH(B56,SKU!C:C,0)),"") -> BENEFICENCIA SP | R56: =IF(COUNTIF(ROMANEIOS!K:K,A56)>0,J56,"")
A57: =IFERROR(INDEX(NFS!F:F,MATCH(B57,NFS!E:E,0)),"") -> 178980 | B57: 69394 | C57: CLAUDIO | D57: 46304 | E57: =IF(B57="","",COUNTIF(SKU!C:C,B57)) -> 2 | F57: CARRO PROPRIO | G57: FATURADO | H57: BACKLOG | I57: =IF(A57="","",IFERROR(VLOOKUP(TEXT(A57,"0"),#REF!,9,FALSE),"")) | K57: =IFERROR(INDEX(#REF!,MATCH(A57,#REF!,0)),"") | L57: =IFERROR(INDEX(SKU!E:E,MATCH(B57,SKU!C:C,0)),"") -> BENEFICENCIA SP | R57: =IF(COUNTIF(ROMANEIOS!K:K,A57)>0,J57,"")
A58: =IFERROR(INDEX(NFS!F:F,MATCH(B58,NFS!E:E,0)),"") -> 178979 | B58: 69395 | C58: CLAUDIO | D58: 46304 | E58: =IF(B58="","",COUNTIF(SKU!C:C,B58)) -> 1 | F58: CARRO PROPRIO | G58: FATURADO | H58: BACKLOG | I58: =IF(A58="","",IFERROR(VLOOKUP(TEXT(A58,"0"),#REF!,9,FALSE),"")) | K58: =IFERROR(INDEX(#REF!,MATCH(A58,#REF!,0)),"") | L58: =IFERROR(INDEX(SKU!E:E,MATCH(B58,SKU!C:C,0)),"") -> BENEFICENCIA SP | R58: =IF(COUNTIF(ROMANEIOS!K:K,A58)>0,J58,"")
A59: =IFERROR(INDEX(NFS!F:F,MATCH(B59,NFS!E:E,0)),"") -> 178883 | B59: 69829 | C59: WELINGTON | D59: 46303 | E59: =IF(B59="","",COUNTIF(SKU!C:C,B59)) -> 1 | F59: CARRO PROPRIO | G59: FATURADO | H59: SAUDAVEL | I59: =IF(A59="","",IFERROR(VLOOKUP(TEXT(A59,"0"),#REF!,9,FALSE),"")) | K59: =IFERROR(INDEX(#REF!,MATCH(A59,#REF!,0)),"") | L59: =IFERROR(INDEX(SKU!E:E,MATCH(B59,SKU!C:C,0)),"") -> CACAU SHOW | R59: =IF(COUNTIF(ROMANEIOS!K:K,A59)>0,J59,"")
A60: =IFERROR(INDEX(NFS!F:F,MATCH(B60,NFS!E:E,0)),"") -> 178873 | B60: 69562 | C60: RAONI | D60: 46303 | E60: =IF(B60="","",COUNTIF(SKU!C:C,B60)) -> 8 | F60: BTA | G60: FATURADO | H60: SAUDAVEL | I60: =IF(A60="","",IFERROR(VLOOKUP(TEXT(A60,"0"),#REF!,9,FALSE),"")) | K60: =IFERROR(INDEX(#REF!,MATCH(A60,#REF!,0)),"") | L60: =IFERROR(INDEX(SKU!E:E,MATCH(B60,SKU!C:C,0)),"") -> LIDERANCA MG | R60: =IF(COUNTIF(ROMANEIOS!K:K,A60)>0,J60,"")
A61: =IFERROR(INDEX(NFS!F:F,MATCH(B61,NFS!E:E,0)),"") -> 179052 | B61: 69417 | C61: CLAUDIO | D61: 46304 | E61: =IF(B61="","",COUNTIF(SKU!C:C,B61)) -> 6 | F61: CARRO PROPRIO | G61: FATURADO | H61: BACKLOG | I61: =IF(A61="","",IFERROR(VLOOKUP(TEXT(A61,"0"),#REF!,9,FALSE),"")) | K61: =IFERROR(INDEX(#REF!,MATCH(A61,#REF!,0)),"") | L61: =IFERROR(INDEX(SKU!E:E,MATCH(B61,SKU!C:C,0)),"") -> BENEFICENCIA SP | R61: =IF(COUNTIF(ROMANEIOS!K:K,A61)>0,J61,"")
A62: =IFERROR(INDEX(NFS!F:F,MATCH(B62,NFS!E:E,0)),"") -> 178985 | B62: 62288 | C62: CLAUDIO | D62: 46304 | E62: =IF(B62="","",COUNTIF(SKU!C:C,B62)) -> 1 | F62: CARRO PROPRIO | G62: FATURADO | H62: BACKLOG | I62: =IF(A62="","",IFERROR(VLOOKUP(TEXT(A62,"0"),#REF!,9,FALSE),"")) | K62: =IFERROR(INDEX(#REF!,MATCH(A62,#REF!,0)),"") | L62: =IFERROR(INDEX(SKU!E:E,MATCH(B62,SKU!C:C,0)),"") -> BENEFICENCIA SP | R62: =IF(COUNTIF(ROMANEIOS!K:K,A62)>0,J62,"")
A63: =IFERROR(INDEX(NFS!F:F,MATCH(B63,NFS!E:E,0)),"") -> 178974 | B63: 65157 | C63: KARINA | D63: 46303 | E63: =IF(B63="","",COUNTIF(SKU!C:C,B63)) -> 3 | F63: CARRO PROPRIO | G63: FATURADO | H63: BACKLOG | I63: =IF(A63="","",IFERROR(VLOOKUP(TEXT(A63,"0"),#REF!,9,FALSE),"")) | K63: =IFERROR(INDEX(#REF!,MATCH(A63,#REF!,0)),"") | L63: =IFERROR(INDEX(SKU!E:E,MATCH(B63,SKU!C:C,0)),"") -> BIOFAST | R63: =IF(COUNTIF(ROMANEIOS!K:K,A63)>0,J63,"")
A64: =IFERROR(INDEX(NFS!F:F,MATCH(B64,NFS!E:E,0)),"") -> 178935 | B64: 69320 | C64: MAURICIO | D64: 46302 | E64: =IF(B64="","",COUNTIF(SKU!C:C,B64)) -> 38 | F64: CARRO PROPRIO | G64: FATURADO | H64: BACKLOG | I64: =IF(A64="","",IFERROR(VLOOKUP(TEXT(A64,"0"),#REF!,9,FALSE),"")) | K64: =IFERROR(INDEX(#REF!,MATCH(A64,#REF!,0)),"") | L64: =IFERROR(INDEX(SKU!E:E,MATCH(B64,SKU!C:C,0)),"") -> CLINICA PREMIUM CARE | R64: =IF(COUNTIF(ROMANEIOS!K:K,A64)>0,J64,"")
A65: =IFERROR(INDEX(NFS!F:F,MATCH(B65,NFS!E:E,0)),"") -> 178929 | B65: 69331 | C65: WELINGTON | D65: 46302 | E65: =IF(B65="","",COUNTIF(SKU!C:C,B65)) -> 41 | F65: CARRO PROPRIO | G65: FATURADO | H65: BACKLOG | I65: =IF(A65="","",IFERROR(VLOOKUP(TEXT(A65,"0"),#REF!,9,FALSE),"")) | K65: =IFERROR(INDEX(#REF!,MATCH(A65,#REF!,0)),"") | L65: =IFERROR(INDEX(SKU!E:E,MATCH(B65,SKU!C:C,0)),"") -> CLINICA PREMIUM CARE | R65: =IF(COUNTIF(ROMANEIOS!K:K,A65)>0,J65,"")
A66: =IFERROR(INDEX(NFS!F:F,MATCH(B66,NFS!E:E,0)),"") -> 178987 | B66: 69393 | C66: MAURICIO | D66: 46303 | E66: =IF(B66="","",COUNTIF(SKU!C:C,B66)) -> 34 | F66: CARRO PROPRIO | G66: FATURADO | H66: BACKLOG | I66: =IF(A66="","",IFERROR(VLOOKUP(TEXT(A66,"0"),#REF!,9,FALSE),"")) | K66: =IFERROR(INDEX(#REF!,MATCH(A66,#REF!,0)),"") | L66: =IFERROR(INDEX(SKU!E:E,MATCH(B66,SKU!C:C,0)),"") -> CLINICA PREMIUM CARE | R66: =IF(COUNTIF(ROMANEIOS!K:K,A66)>0,J66,"")
A67: =IFERROR(INDEX(NFS!F:F,MATCH(B67,NFS!E:E,0)),"") -> 179012 | B67: 69332 | C67: RAPHAEL | D67: 46304 | E67: =IF(B67="","",COUNTIF(SKU!C:C,B67)) -> 38 | F67: CARRO PROPRIO | G67: FATURADO | H67: BACKLOG | I67: =IF(A67="","",IFERROR(VLOOKUP(TEXT(A67,"0"),#REF!,9,FALSE),"")) | K67: =IFERROR(INDEX(#REF!,MATCH(A67,#REF!,0)),"") | L67: =IFERROR(INDEX(SKU!E:E,MATCH(B67,SKU!C:C,0)),"") -> CLINICA PREMIUM CARE | R67: =IF(COUNTIF(ROMANEIOS!K:K,A67)>0,J67,"")
A68: =IFERROR(INDEX(NFS!F:F,MATCH(B68,NFS!E:E,0)),"") -> 178881 | B68: 69560 | C68: RAONI | D68: 46303 | E68: =IF(B68="","",COUNTIF(SKU!C:C,B68)) -> 1 | F68: BTA | G68: FATURADO | H68: SAUDAVEL | I68: =IF(A68="","",IFERROR(VLOOKUP(TEXT(A68,"0"),#REF!,9,FALSE),"")) | K68: =IFERROR(INDEX(#REF!,MATCH(A68,#REF!,0)),"") | L68: =IFERROR(INDEX(SKU!E:E,MATCH(B68,SKU!C:C,0)),"") -> LIDERANCA MG | R68: =IF(COUNTIF(ROMANEIOS!K:K,A68)>0,J68,"")
... A73: =IFERROR(INDEX(NFS!F:F,MATCH(B73,NFS!E:E,0)),"") -> 179205 | B73: 69653 | C73: MAURICIO | D73: 46303 | E73: =IF(B73="","",COUNTIF(SKU!C:C,B73)) -> 4 | F73: CARRO PROPRIO | G73: SEPARANDO | H73: SAUDAVEL | I73: =IF(A73="","",IFERROR(VLOOKUP(TEXT(A73,"0"),#REF!,9,FALSE),"")) | K73: =IFERROR(INDEX(#REF!,MATCH(A73,#REF!,0)),"") | L73: =IFERROR(INDEX(SKU!E:E,MATCH(B73,SKU!C:C,0)),"") -> SAO CAMILO IPIRANGA | R73: =IF(COUNTIF(ROMANEIOS!K:K,A73)>0,J73,"")
A74: =IFERROR(INDEX(NFS!F:F,MATCH(B74,NFS!E:E,0)),"") -> 178954 | B74: 69625 | C74: JESSICA | D74: 46303 | E74: 5 | F74: CARRO PROPRIO | G74: FATURADO | H74: SAUDAVEL | I74: =IF(A74="","",IFERROR(VLOOKUP(TEXT(A74,"0"),#REF!,9,FALSE),"")) | K74: =IFERROR(INDEX(#REF!,MATCH(A74,#REF!,0)),"") | L74: HOSPITAL ALBERT EINSTEN | R74: =IF(COUNTIF(ROMANEIOS!K:K,A74)>0,J74,"")
A75: =IFERROR(INDEX(NFS!F:F,MATCH(B75,NFS!E:E,0)),"") -> 178922 | B75: 69479 | C75: LEANDRO | D75: 46303 | E75: =IF(B75="","",COUNTIF(SKU!C:C,B75)) -> 1 | F75: CARRO PROPRIO | G75: FATURADO | H75: BACKLOG | I75: =IF(A75="","",IFERROR(VLOOKUP(TEXT(A75,"0"),#REF!,9,FALSE),"")) | K75: =IFERROR(INDEX(#REF!,MATCH(A75,#REF!,0)),"") | L75: =IFERROR(INDEX(SKU!E:E,MATCH(B75,SKU!C:C,0)),"") -> DASA 45.796.554/0003 | R75: =IF(COUNTIF(ROMANEIOS!K:K,A75)>0,J75,"")
A76: =IFERROR(INDEX(NFS!F:F,MATCH(B76,NFS!E:E,0)),"") -> 178924 | B76: 69438 | C76: LEANDRO | D76: 46303 | E76: =IF(B76="","",COUNTIF(SKU!C:C,B76)) -> 4 | F76: CARRO PROPRIO | G76: FATURADO | H76: BACKLOG | I76: =IF(A76="","",IFERROR(VLOOKUP(TEXT(A76,"0"),#REF!,9,FALSE),"")) | K76: =IFERROR(INDEX(#REF!,MATCH(A76,#REF!,0)),"") | L76: =IFERROR(INDEX(SKU!E:E,MATCH(B76,SKU!C:C,0)),"") -> DASA 45.796.554/0011 | R76: =IF(COUNTIF(ROMANEIOS!K:K,A76)>0,J76,"")
A77: =IFERROR(INDEX(NFS!F:F,MATCH(B77,NFS!E:E,0)),"") -> 178902 | B77: 68990 | C77: LEANDRO | D77: 46303 | E77: =IF(B77="","",COUNTIF(SKU!C:C,B77)) -> 4 | F77: CARRO PROPRIO | G77: FATURADO | H77: BACKLOG | I77: =IF(A77="","",IFERROR(VLOOKUP(TEXT(A77,"0"),#REF!,9,FALSE),"")) | K77: =IFERROR(INDEX(#REF!,MATCH(A77,#REF!,0)),"") | L77: =IFERROR(INDEX(SKU!E:E,MATCH(B77,SKU!C:C,0)),"") -> DASA 61.486.650/0273 | R77: =IF(COUNTIF(ROMANEIOS!K:K,A77)>0,J77,"")
A78: =IFERROR(INDEX(NFS!F:F,MATCH(B78,NFS!E:E,0)),"") -> 178845 | B78: 68655 | C78: RAONI | D78: 46302 | E78: =IF(B78="","",COUNTIF(SKU!C:C,B78)) -> 3 | F78: CARRO PROPRIO | G78: FATURADO | H78: BACKLOG | L78: =IFERROR(INDEX(SKU!E:E,MATCH(B78,SKU!C:C,0)),"") -> DASA ALTA EXCELENCIA | R78: =IF(COUNTIF(ROMANEIOS!K:K,A78)>0,J78,"")
A79: =IFERROR(INDEX(NFS!F:F,MATCH(B79,NFS!E:E,0)),"") -> 178923 | B79: 69287 | C79: LEANDRO | D79: 46303 | E79: =IF(B79="","",COUNTIF(SKU!C:C,B79)) -> 2 | F79: CARRO PROPRIO | G79: FATURADO | H79: BACKLOG | I79: =IF(A79="","",IFERROR(VLOOKUP(TEXT(A79,"0"),#REF!,9,FALSE),"")) | K79: =IFERROR(INDEX(#REF!,MATCH(A79,#REF!,0)),"") | L79: =IFERROR(INDEX(SKU!E:E,MATCH(B79,SKU!C:C,0)),"") -> DASA CIENTIFICALAB | R79: =IF(COUNTIF(ROMANEIOS!K:K,A79)>0,J79,"")
A80: =IFERROR(INDEX(NFS!F:F,MATCH(B80,NFS!E:E,0)),"") -> 179014 | B80: 69436 | C80: GLEICE | D80: 46304 | E80: =IF(B80="","",COUNTIF(SKU!C:C,B80)) -> 2 | F80: RISSO | G80: FATURADO | H80: BACKLOG | I80: =IF(A80="","",IFERROR(VLOOKUP(TEXT(A80,"0"),#REF!,9,FALSE),"")) | K80: =IFERROR(INDEX(#REF!,MATCH(A80,#REF!,0)),"") | L80: =IFERROR(INDEX(SKU!E:E,MATCH(B80,SKU!C:C,0)),"") -> DASA CIENTIFICALAB | R80: =IF(COUNTIF(ROMANEIOS!K:K,A80)>0,J80,"")
A81: =IFERROR(INDEX(NFS!F:F,MATCH(B81,NFS!E:E,0)),"") -> 178960 | B81: 68937 | C81: RAONI | D81: 46303 | E81: =IF(B81="","",COUNTIF(SKU!C:C,B81)) -> 3 | F81: CARRO PROPRIO | G81: FATURADO | H81: BACKLOG | I81: =IF(A81="","",IFERROR(VLOOKUP(TEXT(A81,"0"),#REF!,9,FALSE),"")) | K81: =IFERROR(INDEX(#REF!,MATCH(A81,#REF!,0)),"") | L81: =IFERROR(INDEX(SKU!E:E,MATCH(B81,SKU!C:C,0)),"") -> DASA CTO BORIS BEREN | R81: =IF(COUNTIF(ROMANEIOS!K:K,A81)>0,J81,"")
A82: =IFERROR(INDEX(NFS!F:F,MATCH(B82,NFS!E:E,0)),"") -> 178971 | B82: 68813 | C82: JOÃO PAULO | D82: 46304 | E82: =IF(B82="","",COUNTIF(SKU!C:C,B82)) -> 10 | F82: BROS | G82: FATURADO | H82: BACKLOG | I82: =IF(A82="","",IFERROR(VLOOKUP(TEXT(A82,"0"),#REF!,9,FALSE),"")) | K82: =IFERROR(INDEX(#REF!,MATCH(A82,#REF!,0)),"") | L82: =IFERROR(INDEX(SKU!E:E,MATCH(B82,SKU!C:C,0)),"") -> DASA DF | R82: =IF(COUNTIF(ROMANEIOS!K:K,A82)>0,J82,"")
A83: =IFERROR(INDEX(NFS!F:F,MATCH(B83,NFS!E:E,0)),"") -> 178830 | B83: 69274 | C83: RAONI | D83: 46302 | E83: =IF(B83="","",COUNTIF(SKU!C:C,B83)) -> 1 | F83: CARRO PROPRIO | G83: FATURADO | H83: BACKLOG | L83: =IFERROR(INDEX(SKU!E:E,MATCH(B83,SKU!C:C,0)),"") -> DASA DIAGNOSTICO | R83: =IF(COUNTIF(ROMANEIOS!K:K,A83)>0,J83,"")
A84: =IFERROR(INDEX(NFS!F:F,MATCH(B84,NFS!E:E,0)),"") -> 178853 | B84: 68521 | C84: RAONI | D84: 46302 | E84: =IF(B84="","",COUNTIF(SKU!C:C,B84)) -> 2 | F84: CARRO PROPRIO | G84: FATURADO | H84: BACKLOG | L84: =IFERROR(INDEX(SKU!E:E,MATCH(B84,SKU!C:C,0)),"") -> DASA DIAGNOSTICO | R84: =IF(COUNTIF(ROMANEIOS!K:K,A84)>0,J84,"")
A85: =IFERROR(INDEX(NFS!F:F,MATCH(B85,NFS!E:E,0)),"") -> 178925 | B85: 69555 | C85: LEANDRO | D85: 46303 | E85: =IF(B85="","",COUNTIF(SKU!C:C,B85)) -> 3 | F85: CARRO PROPRIO | G85: FATURADO | H85: BACKLOG | I85: =IF(A85="","",IFERROR(VLOOKUP(TEXT(A85,"0"),#REF!,9,FALSE),"")) | K85: =IFERROR(INDEX(#REF!,MATCH(A85,#REF!,0)),"") | L85: =IFERROR(INDEX(SKU!E:E,MATCH(B85,SKU!C:C,0)),"") -> DASA DIAGNOSTICO | R85: =IF(COUNTIF(ROMANEIOS!K:K,A85)>0,J85,"")
A86: =IFERROR(INDEX(NFS!F:F,MATCH(B86,NFS!E:E,0)),"") -> 178907 | B86: 69666 | C86: LEANDRO | D86: 46303 | E86: =IF(B86="","",COUNTIF(SKU!C:C,B86)) -> 6 | F86: CARRO PROPRIO | G86: FATURADO | H86: BACKLOG | I86: =IF(A86="","",IFERROR(VLOOKUP(TEXT(A86,"0"),#REF!,9,FALSE),"")) | K86: =IFERROR(INDEX(#REF!,MATCH(A86,#REF!,0)),"") | L86: =IFERROR(INDEX(SKU!E:E,MATCH(B86,SKU!C:C,0)),"") -> DASA DIAGNOSTICO | R86: =IF(COUNTIF(ROMANEIOS!K:K,A86)>0,J86,"")
A87: =IFERROR(INDEX(NFS!F:F,MATCH(B87,NFS!E:E,0)),"") -> 178917 | B87: 69670 | C87: LEANDRO | D87: 46303 | E87: =IF(B87="","",COUNTIF(SKU!C:C,B87)) -> 5 | F87: CARRO PROPRIO | G87: FATURADO | H87: BACKLOG | I87: =IF(A87="","",IFERROR(VLOOKUP(TEXT(A87,"0"),#REF!,9,FALSE),"")) | K87: =IFERROR(INDEX(#REF!,MATCH(A87,#REF!,0)),"") | L87: =IFERROR(INDEX(SKU!E:E,MATCH(B87,SKU!C:C,0)),"") -> DASA DIAGNOSTICO | R87: =IF(COUNTIF(ROMANEIOS!K:K,A87)>0,J87,"")
A88: =IFERROR(INDEX(NFS!F:F,MATCH(B88,NFS!E:E,0)),"") -> 178908 | B88: 69667 | C88: LEANDRO | D88: 46303 | E88: =IF(B88="","",COUNTIF(SKU!C:C,B88)) -> 5 | F88: CARRO PROPRIO | G88: FATURADO | H88: BACKLOG | I88: =IF(A88="","",IFERROR(VLOOKUP(TEXT(A88,"0"),#REF!,9,FALSE),"")) | K88: =IFERROR(INDEX(#REF!,MATCH(A88,#REF!,0)),"") | L88: =IFERROR(INDEX(SKU!E:E,MATCH(B88,SKU!C:C,0)),"") -> DASA DIAGNOSTICO | R88: =IF(COUNTIF(ROMANEIOS!K:K,A88)>0,J88,"")
A89: =IFERROR(INDEX(NFS!F:F,MATCH(B89,NFS!E:E,0)),"") -> 178894 | B89: 69211 | C89: LEANDRO | D89: 46303 | E89: =IF(B89="","",COUNTIF(SKU!C:C,B89)) -> 1 | F89: CARRO PROPRIO | G89: FATURADO | H89: BACKLOG | I89: =IF(A89="","",IFERROR(VLOOKUP(TEXT(A89,"0"),#REF!,9,FALSE),"")) | K89: =IFERROR(INDEX(#REF!,MATCH(A89,#REF!,0)),"") | L89: =IFERROR(INDEX(SKU!E:E,MATCH(B89,SKU!C:C,0)),"") -> DASA HOSP 9 DE JULHO | R89: =IF(COUNTIF(ROMANEIOS!K:K,A89)>0,J89,"")
A90: =IFERROR(INDEX(NFS!F:F,MATCH(B90,NFS!E:E,0)),"") -> 178918 | B90: 69284 | C90: MARIAH | D90: 46304 | E90: =IF(B90="","",COUNTIF(SKU!C:C,B90)) -> 5 | F90: CARRO PROPRIO | G90: FATURADO | H90: BACKLOG | I90: =IF(A90="","",IFERROR(VLOOKUP(TEXT(A90,"0"),#REF!,9,FALSE),"")) | K90: =IFERROR(INDEX(#REF!,MATCH(A90,#REF!,0)),"") | L90: =IFERROR(INDEX(SKU!E:E,MATCH(B90,SKU!C:C,0)),"") -> DASA HOSP 9 DE JULHO | R90: =IF(COUNTIF(ROMANEIOS!K:K,A90)>0,J90,"")
A91: =IFERROR(INDEX(NFS!F:F,MATCH(B91,NFS!E:E,0)),"") -> 178892 | B91: 69642 | C91: LEANDRO | D91: 46303 | E91: =IF(B91="","",COUNTIF(SKU!C:C,B91)) -> 7 | F91: CARRO PROPRIO | G91: FATURADO | H91: BACKLOG | I91: =IF(A91="","",IFERROR(VLOOKUP(TEXT(A91,"0"),#REF!,9,FALSE),"")) | K91: =IFERROR(INDEX(#REF!,MATCH(A91,#REF!,0)),"") | L91: =IFERROR(INDEX(SKU!E:E,MATCH(B91,SKU!C:C,0)),"") -> DASA IBIRAPUERA | R91: =IF(COUNTIF(ROMANEIOS!K:K,A91)>0,J91,"")
A92: =IFERROR(INDEX(NFS!F:F,MATCH(B92,NFS!E:E,0)),"") -> 178993 | B92: 68789 | C92: WELINGTON | D92: 46304 | E92: =IF(B92="","",COUNTIF(SKU!C:C,B92)) -> 3 | F92: CARRO PROPRIO | G92: FATURADO | H92: BACKLOG | I92: =IF(A92="","",IFERROR(VLOOKUP(TEXT(A92,"0"),#REF!,9,FALSE),"")) | K92: =IFERROR(INDEX(#REF!,MATCH(A92,#REF!,0)),"") | L92: =IFERROR(INDEX(SKU!E:E,MATCH(B92,SKU!C:C,0)),"") -> DASA IMPAR | R92: =IF(COUNTIF(ROMANEIOS!K:K,A92)>0,J92,"")
A93: =IFERROR(INDEX(NFS!F:F,MATCH(B93,NFS!E:E,0)),"") -> 178901 | B93: 69235 | C93: LEANDRO | D93: 46303 | E93: =IF(B93="","",COUNTIF(SKU!C:C,B93)) -> 3 | F93: CARRO PROPRIO | G93: FATURADO | H93: BACKLOG | I93: =IF(A93="","",IFERROR(VLOOKUP(TEXT(A93,"0"),#REF!,9,FALSE),"")) | K93: =IFERROR(INDEX(#REF!,MATCH(A93,#REF!,0)),"") | L93: =IFERROR(INDEX(SKU!E:E,MATCH(B93,SKU!C:C,0)),"") -> DASA INNOVA HOSP | R93: =IF(COUNTIF(ROMANEIOS!K:K,A93)>0,J93,"")
A94: =IFERROR(INDEX(NFS!F:F,MATCH(B94,NFS!E:E,0)),"") -> 178905 | B94: 68999 | C94: LEANDRO | D94: 46303 | E94: =IF(B94="","",COUNTIF(SKU!C:C,B94)) -> 5 | F94: CARRO PROPRIO | G94: FATURADO | H94: BACKLOG | I94: =IF(A94="","",IFERROR(VLOOKUP(TEXT(A94,"0"),#REF!,9,FALSE),"")) | K94: =IFERROR(INDEX(#REF!,MATCH(A94,#REF!,0)),"") | L94: =IFERROR(INDEX(SKU!E:E,MATCH(B94,SKU!C:C,0)),"") -> DASA IPIRANGA | R94: =IF(COUNTIF(ROMANEIOS!K:K,A94)>0,J94,"")
A95: =IFERROR(INDEX(NFS!F:F,MATCH(B95,NFS!E:E,0)),"") -> 178904 | B95: 68994 | C95: LEANDRO | D95: 46303 | E95: =IF(B95="","",COUNTIF(SKU!C:C,B95)) -> 3 | F95: CARRO PROPRIO | G95: FATURADO | H95: BACKLOG | I95: =IF(A95="","",IFERROR(VLOOKUP(TEXT(A95,"0"),#REF!,9,FALSE),"")) | K95: =IFERROR(INDEX(#REF!,MATCH(A95,#REF!,0)),"") | L95: =IFERROR(INDEX(SKU!E:E,MATCH(B95,SKU!C:C,0)),"") -> DASA ITAIM BIBI | R95: =IF(COUNTIF(ROMANEIOS!K:K,A95)>0,J95,"")
A96: =IFERROR(INDEX(NFS!F:F,MATCH(B96,NFS!E:E,0)),"") -> 178909 | B96: 69742 | C96: LEANDRO | D96: 46303 | E96: =IF(B96="","",COUNTIF(SKU!C:C,B96)) -> 4 | F96: CARRO PROPRIO | G96: FATURADO | H96: SAUDAVEL | I96: =IF(A96="","",IFERROR(VLOOKUP(TEXT(A96,"0"),#REF!,9,FALSE),"")) | K96: =IFERROR(INDEX(#REF!,MATCH(A96,#REF!,0)),"") | L96: =IFERROR(INDEX(SKU!E:E,MATCH(B96,SKU!C:C,0)),"") -> DASA DIAGNOSTICO | R96: =IF(COUNTIF(ROMANEIOS!K:K,A96)>0,J96,"")
... A109: =IFERROR(INDEX(NFS!F:F,MATCH(B109,NFS!E:E,0)),"") -> 178920 | B109: 65952 | C109: LEANDRO | D109: 46303 | E109: =IF(B109="","",COUNTIF(SKU!C:C,B109)) -> 2 | F109: CARRO PROPRIO | G109: FATURADO | H109: SAUDAVEL | I109: =IF(A109="","",IFERROR(VLOOKUP(TEXT(A109,"0"),#REF!,9,FALSE),"")) | K109: =IFERROR(INDEX(#REF!,MATCH(A109,#REF!,0)),"") | L109: =IFERROR(INDEX(SKU!E:E,MATCH(B109,SKU!C:C,0)),"") -> TECNOLAB | R109: =IF(COUNTIF(ROMANEIOS!K:K,A109)>0,J109,"")
A110: =IFERROR(INDEX(NFS!F:F,MATCH(B110,NFS!E:E,0)),"") -> 178946 | B110: 69617 | C110: WELINGTON | D110: 46303 | E110: 2 | F110: CARRO PROPRIO | G110: FATURADO | H110: SAUDAVEL | I110: =IF(A110="","",IFERROR(VLOOKUP(TEXT(A110,"0"),#REF!,9,FALSE),"")) | K110: =IFERROR(INDEX(#REF!,MATCH(A110,#REF!,0)),"") | L110: SOC BENEF ISRAELITABRAS HOSPITAL ALBERT | R110: =IF(COUNTIF(ROMANEIOS!K:K,A110)>0,J110,"")
A111: =IFERROR(INDEX(NFS!F:F,MATCH(B111,NFS!E:E,0)),"") -> 179285 | B111: 69587 | C111: MIJOHNSON | D111: 46307 | E111: =IF(B111="","",COUNTIF(SKU!C:C,B111)) -> 17 | F111: CARRO PROPRIO | G111: SEPARANDO | H111: BACKLOG | I111: =IF(A111="","",IFERROR(VLOOKUP(TEXT(A111,"0"),#REF!,9,FALSE),"")) | K111: =IFERROR(INDEX(#REF!,MATCH(A111,#REF!,0)),"") | L111: =IFERROR(INDEX(SKU!E:E,MATCH(B111,SKU!C:C,0)),"") -> PLANOVA | R111: =IF(COUNTIF(ROMANEIOS!K:K,A111)>0,J111,"")
A112: =IFERROR(INDEX(NFS!F:F,MATCH(B112,NFS!E:E,0)),"") -> 178900 | B112: 69471 | C112: LEANDRO | D112: 46303 | E112: =IF(B112="","",COUNTIF(SKU!C:C,B112)) -> 3 | F112: CARRO PROPRIO | G112: FATURADO | H112: BACKLOG | I112: =IF(A112="","",IFERROR(VLOOKUP(TEXT(A112,"0"),#REF!,9,FALSE),"")) | K112: =IFERROR(INDEX(#REF!,MATCH(A112,#REF!,0)),"") | L112: =IFERROR(INDEX(SKU!E:E,MATCH(B112,SKU!C:C,0)),"") -> DASA LAB CLINICO | R112: =IF(COUNTIF(ROMANEIOS!K:K,A112)>0,J112,"")
A113: =IFERROR(INDEX(NFS!F:F,MATCH(B113,NFS!E:E,0)),"") -> 178884 | B113: 69286 | C113: MAURICIO | D113: 46303 | E113: =IF(B113="","",COUNTIF(SKU!C:C,B113)) -> 2 | F113: CARRO PROPRIO | G113: FATURADO | H113: BACKLOG | I113: =IF(A113="","",IFERROR(VLOOKUP(TEXT(A113,"0"),#REF!,9,FALSE),"")) | K113: =IFERROR(INDEX(#REF!,MATCH(A113,#REF!,0)),"") | L113: =IFERROR(INDEX(SKU!E:E,MATCH(B113,SKU!C:C,0)),"") -> DASA PERDIZES | R113: =IF(COUNTIF(ROMANEIOS!K:K,A113)>0,J113,"")
A114: =IFERROR(INDEX(NFS!F:F,MATCH(B114,NFS!E:E,0)),"") -> 178992 | B114: 69747 | C114: PAIVA | D114: 46304 | E114: =IF(B114="","",COUNTIF(SKU!C:C,B114)) -> 10 | F114: PACIFICO | G114: FATURADO | H114: BACKLOG | I114: =IF(A114="","",IFERROR(VLOOKUP(TEXT(A114,"0"),#REF!,9,FALSE),"")) | K114: =IFERROR(INDEX(#REF!,MATCH(A114,#REF!,0)),"") | L114: =IFERROR(INDEX(SKU!E:E,MATCH(B114,SKU!C:C,0)),"") -> DASA RECIFE 61.486.6 | R114: =IF(COUNTIF(ROMANEIOS!K:K,A114)>0,J114,"")
A115: =IFERROR(INDEX(NFS!F:F,MATCH(B115,NFS!E:E,0)),"") -> 178981 | B115: 68865 | C115: GLEICE | D115: 46304 | E115: =IF(B115="","",COUNTIF(SKU!C:C,B115)) -> 2 | F115: PACIFICO | G115: FATURADO | H115: BACKLOG | I115: =IF(A115="","",IFERROR(VLOOKUP(TEXT(A115,"0"),#REF!,9,FALSE),"")) | K115: =IFERROR(INDEX(#REF!,MATCH(A115,#REF!,0)),"") | L115: =IFERROR(INDEX(SKU!E:E,MATCH(B115,SKU!C:C,0)),"") -> DASA RECIFE 61.486.6 | R115: =IF(COUNTIF(ROMANEIOS!K:K,A115)>0,J115,"")
A116: =IFERROR(INDEX(NFS!F:F,MATCH(B116,NFS!E:E,0)),"") -> 178921 | B116: 69472 | C116: LEANDRO | D116: 46303 | E116: =IF(B116="","",COUNTIF(SKU!C:C,B116)) -> 4 | F116: CARRO PROPRIO | G116: FATURADO | H116: BACKLOG | I116: =IF(A116="","",IFERROR(VLOOKUP(TEXT(A116,"0"),#REF!,9,FALSE),"")) | K116: =IFERROR(INDEX(#REF!,MATCH(A116,#REF!,0)),"") | L116: =IFERROR(INDEX(SKU!E:E,MATCH(B116,SKU!C:C,0)),"") -> DASA SALOMAO E ZOPPI | R116: =IF(COUNTIF(ROMANEIOS!K:K,A116)>0,J116,"")
...

Sheet NFS
A1: Filial | B1: EmissÃ£o | C1: Cliente | D1: Nome Fantasia | E1: PV | F1: Nr.NF | G1: Serie | H1: R$ Merc. | I1: Chave | J1: Cod.Transp. | K1: Transportador | L1: Tp.Frete | M1: % Frete | N1: CC-e
A2: 101 | B2: 46237 | C2: 000020-104 | D2: DASA HOSP 9 DE JULHO | E2: 64211 | F2: 172826 | G2: 1 | H2: 21998.76 | I2: 3.5260812e+43 | J2: 32 | K2: CARRO PROPRIO | L2: C
A3: 101 | B3: 46237 | C3: 000111-001 | D3: DASA INNOVA HOSP | E3: 63932 | F3: 172827 | G3: 1 | H3: 1108.1 | I3: 3.5260812e+43 | J3: 32 | K3: CARRO PROPRIO | L3: C
A4: 101 | B4: 46237 | C4: 000024-003 | D4: ALBERT EINSTEIN | E4: 62391 | F4: 172828 | G4: 1 | H4: 200.43 | I4: 3.5260812e+43 | J4: 32 | K4: CARRO PROPRIO | L4: C
A5: 101 | B5: 46237 | C5: 000060-001 | D5: HOSP SANTA CATARINA | E5: 64184 | F5: 172832 | G5: 1 | H5: 31942.95 | I5: 3.5260812e+43 | J5: 32 | K5: CARRO PROPRIO | L5: C
A6: 101 | B6: 46237 | C6: 000024-002 | D6: ALBERT EINSTEIN | E6: 60104 | F6: 172833 | G6: 1 | H6: 42997.5 | I6: 3.5260812e+43 | J6: 32 | K6: CARRO PROPRIO | L6: C
A7: 101 | B7: 46237 | C7: 000034-001 | D7: OSWALDO CRUZ SP | E7: 64082 | F7: 172834 | G7: 1 | H7: 9686.38 | I7: 3.5260812e+43 | J7: 32 | K7: CARRO PROPRIO | L7: C
A8: 101 | B8: 46237 | C8: 000020-178 | D8: DASA SSZ 45.796.554/ | E8: 63737 | F8: 172835 | G8: 1 | H8: 6093.68 | I8: 3.5260812e+43 | J8: 32 | K8: CARRO PROPRIO | L8: C
A9: 101 | B9: 46237 | C9: 001240-007 | D9: SIRIO LIBANES | E9: 63646 | F9: 172836 | G9: 1 | H9: 41324.5 | I9: 3.5260812e+43 | J9: 32 | K9: CARRO PROPRIO | L9: C
A10: 101 | B10: 46237 | C10: 001240-007 | D10: SIRIO LIBANES | E10: 63929 | F10: 172837 | G10: 1 | H10: 24737.36 | I10: 3.5260812e+43 | J10: 32 | K10: CARRO PROPRIO | L10: C
A11: 101 | B11: 46237 | C11: 001240-007 | D11: SIRIO LIBANES | E11: 63742 | F11: 172838 | G11: 1 | H11: 19361.62 | I11: 3.5260812e+43 | J11: 32 | K11: CARRO PROPRIO | L11: C
A12: 101 | B12: 46237 | C12: 001240-007 | D12: SIRIO LIBANES | E12: 64141 | F12: 172839 | G12: 1 | H12: 22374.6 | I12: 3.5260812e+43 | J12: 32 | K12: CARRO PROPRIO | L12: C
A13: 101 | B13: 46237 | C13: 001240-007 | D13: SIRIO LIBANES | E13: 54836 | F13: 172840 | G13: 1 | H13: 4500 | I13: 3.5260812e+43 | J13: 32 | K13: CARRO PROPRIO | L13: C
... A41: 101 | B41: 46238 | C41: 000024-003 | D41: ALBERT EINSTEIN | E41: 63977 | F41: 172871 | G41: 1 | H41: 359.7 | I41: 3.5260812e+43 | J41: 32 | K41: CARRO PROPRIO | L41: C
A42: 101 | B42: 46238 | C42: 000064-020 | D42: SERVI SOCIAL SECONCI | E42: 63938 | F42: 172872 | G42: 1 | H42: 5855.31 | I42: 3.5260812e+43 | J42: 7 | K42: RISSO | L42: C | N42: X
A43: 101 | B43: 46238 | C43: 000020-177 | D43: DASA 61.486.650/1161 | E43: 64252 | F43: 172874 | G43: 1 | H43: 2076.31 | I43: 3.5260812e+43 | J43: 32 | K43: CARRO PROPRIO | L43: C
A44: 101 | B44: 46238 | C44: 000024-003 | D44: ALBERT EINSTEIN | E44: 63976 | F44: 172875 | G44: 1 | H44: 359.7 | I44: 3.5260812e+43 | J44: 32 | K44: CARRO PROPRIO | L44: C
A45: 101 | B45: 46238 | C45: 000064-015 | D45: CHS REG SOROCABA | E45: 64255 | F45: 172876 | G45: 1 | H45: 1145.6 | I45: 3.5260812e+43 | J45: 7 | K45: RISSO | L45: C
A46: 101 | B46: 46238 | C46: 000070-008 | D46: TECNOLAB UNID VIII | E46: 64272 | F46: 172877 | G46: 1 | H46: 1062.6 | I46: 3.5260812e+43 | J46: 32 | K46: CARRO PROPRIO | L46: C
A47: 101 | B47: 46238 | C47: 000894-001 | D47: HOSP SAO VICENTE | E47: 64266 | F47: 172878 | G47: 1 | H47: 525.45 | I47: 3.5260812e+43 | J47: 32 | K47: CARRO PROPRIO | L47: C
A48: 101 | B48: 46238 | C48: 000921-001 | D48: HOSP PROF EDMUNDO VA | E48: 64188 | F48: 172879 | G48: 1 | H48: 886.1 | I48: 3.5260812e+43 | J48: 32 | K48: CARRO PROPRIO | L48: C
A49: 101 | B49: 46238 | C49: 001435-001 | D49: HOSP NIPO BRASILEIRO | E49: 63669 | F49: 172880 | G49: 1 | H49: 10512 | I49: 3.5260812e+43 | J49: 32 | K49: CARRO PROPRIO | L49: C
A50: 101 | B50: 46238 | C50: 001854-001 | D50: CLEANING SOLUTIONS C | E50: 64359 | F50: 172881 | G50: 1 | H50: 1494.85 | I50: 3.5260812e+43 | J50: 32 | K50: CARRO PROPRIO | L50: C
A51: 101 | B51: 46238 | C51: 000024-003 | D51: ALBERT EINSTEIN | E51: 63892 | F51: 172882 | G51: 1 | H51: 1654.35 | I51: 3.5260812e+43 | J51: 32 | K51: CARRO PROPRIO | L51: C
A52: 101 | B52: 46238 | C52: 000049-001 | D52: HOSPITAL MORIAH 19.0 | E52: 63393 | F52: 172883 | G52: 1 | H52: 4402.71 | I52: 3.5260812e+43 | J52: 32 | K52: CARRO PROPRIO | L52: C
A53: 101 | B53: 46238 | C53: 000064-002 | D53: SECONCI MATARAZZO | E53: 64084 | F53: 172884 | G53: 1 | H53: 445.5 | I53: 3.5260812e+43 | J53: 32 | K53: CARRO PROPRIO | L53: C
A54: 101 | B54: 46238 | C54: 000064-002 | D54: SECONCI MATARAZZO | E54: 64145 | F54: 172885 | G54: 1 | H54: 123.1 | I54: 3.5260812e+43 | J54: 32 | K54: CARRO PROPRIO | L54: C
... A60: 101 | B60: 46239 | C60: 000894-001 | D60: HOSP SAO VICENTE | E60: 64404 | F60: 172891 | G60: 1 | H60: 3450 | I60: 3.5260812e+43 | J60: 32 | K60: CARRO PROPRIO | L60: C
A61: 101 | B61: 46239 | C61: 000894-001 | D61: HOSP SAO VICENTE | E61: 64265 | F61: 172892 | G61: 1 | H61: 3065.54 | I61: 3.5260812e+43 | J61: 32 | K61: CARRO PROPRIO | L61: C | N61: X
A62: 101 | B62: 46239 | C62: 000894-001 | D62: HOSP SAO VICENTE | E62: 64267 | F62: 172893 | G62: 1 | H62: 242.73 | I62: 3.5260812e+43 | J62: 32 | K62: CARRO PROPRIO | L62: C
A63: 101 | B63: 46239 | C63: 000894-001 | D63: HOSP SAO VICENTE | E63: 64177 | F63: 172894 | G63: 1 | H63: 256.24 | I63: 3.5260812e+43 | J63: 32 | K63: CARRO PROPRIO | L63: C | N63: X
A64: 101 | B64: 46239 | C64: 000894-001 | D64: HOSP SAO VICENTE | E64: 64186 | F64: 172895 | G64: 1 | H64: 705.35 | I64: 3.5260812e+43 | J64: 32 | K64: CARRO PROPRIO | L64: C
A65: 101 | B65: 46239 | C65: 000894-001 | D65: HOSP SAO VICENTE | E65: 64171 | F65: 172896 | G65: 1 | H65: 520.77 | I65: 3.5260812e+43 | J65: 32 | K65: CARRO PROPRIO | L65: C
A66: 101 | B66: 46239 | C66: 000894-001 | D66: HOSP SAO VICENTE | E66: 64176 | F66: 172897 | G66: 1 | H66: 104.24 | I66: 3.5260812e+43 | J66: 32 | K66: CARRO PROPRIO | L66: C | N66: X
A67: 101 | B67: 46239 | C67: 000894-001 | D67: HOSP SAO VICENTE | E67: 64170 | F67: 172898 | G67: 1 | H67: 104.93 | I67: 3.5260812e+43 | J67: 32 | K67: CARRO PROPRIO | L67: C
A68: 101 | B68: 46239 | C68: 000894-001 | D68: HOSP SAO VICENTE | E68: 64172 | F68: 172899 | G68: 1 | H68: 137.91 | I68: 3.5260812e+43 | J68: 32 | K68: CARRO PROPRIO | L68: C | N68: X
A69: 101 | B69: 46239 | C69: 000894-001 | D69: HOSP SAO VICENTE | E69: 64173 | F69: 172900 | G69: 1 | H69: 763.37 | I69: 3.5260812e+43 | J69: 32 | K69: CARRO PROPRIO | L69: C | N69: X
A70: 101 | B70: 46239 | C70: 000894-001 | D70: HOSP SAO VICENTE | E70: 64245 | F70: 172901 | G70: 1 | H70: 424.98 | I70: 3.5260812e+43 | J70: 32 | K70: CARRO PROPRIO | L70: C
A71: 101 | B71: 46239 | C71: 000894-001 | D71: HOSP SAO VICENTE | E71: 64254 | F71: 172902 | G71: 1 | H71: 15558.77 | I71: 3.5260812e+43 | J71: 32 | K71: CARRO PROPRIO | L71: C | N71: X
A72: 101 | B72: 46239 | C72: 000894-001 | D72: HOSP SAO VICENTE | E72: 64174 | F72: 172903 | G72: 1 | H72: 114.55 | I72: 3.5260812e+43 | J72: 32 | K72: CARRO PROPRIO | L72: C
A73: 101 | B73: 46239 | C73: 000894-001 | D73: HOSP SAO VICENTE | E73: 64175 | F73: 172904 | G73: 1 | H73: 72.3 | I73: 3.5260812e+43 | J73: 32 | K73: CARRO PROPRIO | L73: C | N73: X
A74: 101 | B74: 46239 | C74: 000894-001 | D74: HOSP SAO VICENTE | E74: 64191 | F74: 172905 | G74: 1 | H74: 1618.41 | I74: 3.5260812e+43 | J74: 32 | K74: CARRO PROPRIO | L74: C
A75: 101 | B75: 46239 | C75: 000894-001 | D75: HOSP SAO VICENTE | E75: 64256 | F75: 172906 | G75: 1 | H75: 398.82 | I75: 3.5260812e+43 | J75: 32 | K75: CARRO PROPRIO | L75: C
A76: 101 | B76: 46239 | C76: 000894-001 | D76: HOSP SAO VICENTE | E76: 64413 | F76: 172907 | G76: 1 | H76: 2012.5 | I76: 3.5260812e+43 | L76: C | N76: X
A77: 101 | B77: 46239 | C77: 000003-019 | D77: AFIP CAC GUARULHOS | E77: 63911 | F77: 172908 | G77: 1 | H77: 123.3 | I77: 3.5260812e+43 | J77: 32 | K77: CARRO PROPRIO | L77: C
A78: 101 | B78: 46239 | C78: 000011-001 | D78: BENEFICENCIA SP | E78: 64394 | F78: 172910 | G78: 1 | H78: 14722.5 | I78: 3.5260812e+43 | J78: 32 | K78: CARRO PROPRIO | L78: C | N78: X
A79: 101 | B79: 46239 | C79: 000024-003 | D79: ALBERT EINSTEIN | E79: 63177 | F79: 172911 | G79: 1 | H79: 258.33 | I79: 3.5260812e+43 | J79: 32 | K79: CARRO PROPRIO | L79: C
A80: 101 | B80: 46239 | C80: 000024-003 | D80: ALBERT EINSTEIN | E80: 63322 | F80: 172912 | G80: 1 | H80: 232.5 | I80: 3.5260812e+43 | J80: 32 | K80: CARRO PROPRIO | L80: C
A81: 101 | B81: 46239 | C81: 000024-003 | D81: ALBERT EINSTEIN | E81: 63879 | F81: 172913 | G81: 1 | H81: 232.5 | I81: 3.5260812e+43 | J81: 32 | K81: CARRO PROPRIO | L81: C
A82: 101 | B82: 46239 | C82: 000024-003 | D82: ALBERT EINSTEIN | E82: 63894 | F82: 172914 | G82: 1 | H82: 232.5 | I82: 3.5260812e+43 | J82: 32 | K82: CARRO PROPRIO | L82: C
A83: 101 | B83: 46239 | C83: 000024-003 | D83: ALBERT EINSTEIN | E83: 63978 | F83: 172915 | G83: 1 | H83: 232.5 | I83: 3.5260812e+43 | J83: 32 | K83: CARRO PROPRIO | L83: C
A84: 101 | B84: 46239 | C84: 000024-021 | D84: ALBERT EINSTEIN | E84: 63878 | F84: 172916 | G84: 1 | H84: 387.5 | I84: 3.5260812e+43 | J84: 32 | K84: CARRO PROPRIO | L84: C
A85: 101 | B85: 46239 | C85: 000024-021 | D85: ALBERT EINSTEIN | E85: 63897 | F85: 172917 | G85: 1 | H85: 271.25 | I85: 3.5260812e+43 | J85: 32 | K85: CARRO PROPRIO | L85: C
A86: 101 | B86: 46239 | C86: 000036-003 | D86: HAPVIDA | E86: 64391 | F86: 172918 | G86: 1 | H86: 9821 | I86: 3.5260812e+43 | J86: 32 | K86: CARRO PROPRIO | L86: C
A87: 101 | B87: 46239 | C87: 000036-073 | D87: HAPVIDA | E87: 64277 | F87: 172919 | G87: 1 | H87: 675.5 | I87: 3.5260812e+43 | J87: 7 | K87: RISSO | L87: C
A88: 101 | B88: 46239 | C88: 000049-001 | D88: HOSPITAL MORIAH 19.0 | E88: 63819 | F88: 172920 | G88: 1 | H88: 282.91 | I88: 3.5260812e+43 | J88: 32 | K88: CARRO PROPRIO | L88: C
A89: 101 | B89: 46239 | C89: 000060-011 | D89: H M REGINA PROTMANN | E89: 64200 | F89: 172921 | G89: 1 | H89: 454 | I89: 3.5260812e+43 | J89: 32 | K89: CARRO PROPRIO | L89: C
A90: 101 | B90: 46239 | C90: 000060-011 | D90: H M REGINA PROTMANN | E90: 64201 | F90: 172922 | G90: 1 | H90: 454 | I90: 3.5260812e+43 | J90: 32 | K90: CARRO PROPRIO | L90: C
... A92: 101 | B92: 46239 | C92: 000894-001 | D92: HOSP SAO VICENTE | E92: 64243 | F92: 172924 | G92: 1 | H92: 1931.88 | I92: 3.5260812e+43 | J92: 32 | K92: CARRO PROPRIO | L92: C
A93: 101 | B93: 46239 | C93: 000894-001 | D93: HOSP SAO VICENTE | E93: 64319 | F93: 172925 | G93: 1 | H93: 5968.52 | I93: 3.5260812e+43 | L93: C | N93: X
A94: 101 | B94: 46239 | C94: 000921-001 | D94: HOSP PROF EDMUNDO VA | E94: 64028 | F94: 172926 | G94: 1 | H94: 39 | I94: 3.5260812e+43 | J94: 32 | K94: CARRO PROPRIO | L94: C
A95: 101 | B95: 46239 | C95: 000921-001 | D95: HOSP PROF EDMUNDO VA | E95: 64142 | F95: 172927 | G95: 1 | H95: 4320 | I95: 3.5260812e+43 | J95: 32 | K95: CARRO PROPRIO | L95: C
A96: 101 | B96: 46239 | C96: 001240-007 | D96: SIRIO LIBANES | E96: 64058 | F96: 172928 | G96: 1 | H96: 1230.8 | I96: 3.5260812e+43 | J96: 32 | K96: CARRO PROPRIO | L96: C
A97: 101 | B97: 46239 | C97: 000024-002 | D97: ALBERT EINSTEIN | E97: 62921 | F97: 172929 | G97: 1 | H97: 19800 | I97: 3.5260812e+43 | J97: 32 | K97: CARRO PROPRIO | L97: C
A98: 101 | B98: 46239 | C98: 001240-007 | D98: SIRIO LIBANES | E98: 64059 | F98: 172930 | G98: 1 | H98: 1620.4 | I98: 3.5260812e+43 | J98: 32 | K98: CARRO PROPRIO | L98: C
A99: 101 | B99: 46239 | C99: 001240-007 | D99: SIRIO LIBANES | E99: 64066 | F99: 172931 | G99: 1 | H99: 5760 | I99: 3.5260812e+43 | J99: 32 | K99: CARRO PROPRIO | L99: C
A100: 101 | B100: 46239 | C100: 001240-007 | D100: SIRIO LIBANES | E100: 64217 | F100: 172932 | G100: 1 | H100: 11088 | I100: 3.5260812e+43 | J100: 32 | K100: CARRO PROPRIO | L100: C
A101: 101 | B101: 46239 | C101: 001435-001 | D101: HOSP NIPO BRASILEIRO | E101: 64270 | F101: 172933 | G101: 1 | H101: 5145.6 | I101: 3.5260812e+43 | J101: 32 | K101: CARRO PROPRIO | L101: C
A102: 101 | B102: 46239 | C102: 001435-001 | D102: HOSP NIPO BRASILEIRO | E102: 64271 | F102: 172934 | G102: 1 | H102: 147.57 | I102: 3.5260812e+43 | J102: 32 | K102: CARRO PROPRIO | L102: C
A103: 101 | B103: 46239 | C103: 000011-001 | D103: BENEFICENCIA SP | E103: 64400 | F103: 172935 | G103: 1 | H103: 2418.36 | I103: 3.5260812e+43 | J103: 32 | K103: CARRO PROPRIO | L103: C | N103: X
A104: 101 | B104: 46239 | C104: 000020-238 | D104: DASA DIAGNOSTICO | E104: 63830 | F104: 172936 | G104: 1 | H104: 548.16 | I104: 3.5260812e+43 | J104: 32 | K104: CARRO PROPRIO | L104: C
A105: 101 | B105: 46239 | C105: 000036-003 | D105: HAPVIDA | E105: 63816 | F105: 172937 | G105: 1 | H105: 1034 | I105: 3.5260812e+43 | J105: 32 | K105: CARRO PROPRIO | L105: C
A106: 101 | B106: 46239 | C106: 000036-003 | D106: HAPVIDA | E106: 64234 | F106: 172938 | G106: 1 | H106: 907.2 | I106: 3.5260812e+43 | J106: 32 | K106: CARRO PROPRIO | L106: C
A107: 101 | B107: 46239 | C107: 000036-003 | D107: HAPVIDA | E107: 64374 | F107: 172939 | G107: 1 | H107: 510.3 | I107: 3.5260812e+43 | J107: 32 | K107: CARRO PROPRIO | L107: C
A108: 101 | B108: 46239 | C108: 000036-003 | D108: HAPVIDA | E108: 64382 | F108: 172940 | G108: 1 | H108: 10129.12 | I108: 3.5260812e+43 | J108: 32 | K108: CARRO PROPRIO | L108: C
A109: 101 | B109: 46239 | C109: 000036-003 | D109: HAPVIDA | E109: 64383 | F109: 172941 | G109: 1 | H109: 1498.7 | I109: 3.5260812e+43 | J109: 32 | K109: CARRO PROPRIO | L109: C
A110: 101 | B110: 46239 | C110: 000036-174 | D110: HAPVIDA - SJRP | E110: 64377 | F110: 172942 | G110: 1 | H110: 5703.6 | I110: 3.5260812e+43 | J110: 7 | K110: RISSO | L110: C | N110: X
A111: 101 | B111: 46239 | C111: 000043-007 | D111: LIDERANCA DF | E111: 64345 | F111: 172943 | G111: 1 | H111: 1386.87 | I111: 3.5260812e+43 | J111: 16 | K111: BTA TRANSPORTE | L111: C
A112: 101 | B112: 46239 | C112: 000060-011 | D112: H M REGINA PROTMANN | E112: 64194 | F112: 172944 | G112: 1 | H112: 1211.6 | I112: 3.5260812e+43 | J112: 32 | K112: CARRO PROPRIO | L112: C
A113: 101 | B113: 46239 | C113: 000060-011 | D113: H M REGINA PROTMANN | E113: 64196 | F113: 172945 | G113: 1 | H113: 746.3 | I113: 3.5260812e+43 | J113: 32 | K113: CARRO PROPRIO | L113: C
A114: 101 | B114: 46239 | C114: 000060-011 | D114: H M REGINA PROTMANN | E114: 64197 | F114: 172946 | G114: 1 | H114: 348.4 | I114: 3.5260812e+43 | J114: 32 | K114: CARRO PROPRIO | L114: C
A115: 101 | B115: 46239 | C115: 000060-011 | D115: H M REGINA PROTMANN | E115: 64199 | F115: 172947 | G115: 1 | H115: 348.4 | I115: 3.5260812e+43 | J115: 32 | K115: CARRO PROPRIO | L115: C
A116: 101 | B116: 46239 | C116: 000894-001 | D116: HOSP SAO VICENTE | E116: 64261 | F116: 172948 | G116: 1 | H116: 367.07 | I116: 3.5260812e+43 | J116: 32 | K116: CARRO PROPRIO | L116: C
A117: 101 | B117: 46239 | C117: 000921-001 | D117: HOSP PROF EDMUNDO VA | E117: 64086 | F117: 172949 | G117: 1 | H117: 1513 | I117: 3.5260812e+43 | J117: 32 | K117: CARRO PROPRIO | L117: C
A118: 101 | B118: 46239 | C118: 001240-007 | D118: SIRIO LIBANES | E118: 64221 | F118: 172950 | G118: 1 | H118: 854.62 | I118: 3.5260812e+43 | J118: 32 | K118: CARRO PROPRIO | L118: C
A119: 101 | B119: 46239 | C119: 003310-001 | D119: CLINICA PREMIUM CARE | E119: 64380 | F119: 172951 | G119: 1 | H119: 894.2 | I119: 3.5260812e+43 | J119: 32 | K119: CARRO PROPRIO | L119: C
A120: 101 | B120: 46239 | C120: 000001-003 | D120: MASTER HIGIMED CAMPI | E120: 64020 | F120: 172952 | G120: 1 | H120: 4305.4 | I120: 3.5260812e+43 | J120: 32 | K120: CARRO PROPRIO | L120: C
A121: 101 | B121: 46239 | C121: 000030-001 | D121: MARIO COVAS | E121: 64356 | F121: 172953 | G121: 1 | H121: 2793.6 | I121: 3.5260812e+43 | J121: 63 | K121: CARRO TECNICA | L121: C
A122: 101 | B122: 46239 | C122: 000036-003 | D122: HAPVIDA | E122: 63815 | F122: 172954 | G122: 1 | H122: 6951 | I122: 3.5260812e+43 | J122: 32 | K122: CARRO PROPRIO | L122: C
... A128: 101 | B128: 46239 | C128: 000020-200 | D128: DASA DIAGNOSTICO | E128: 64004 | F128: 172960 | G128: 1 | H128: 158.3 | I128: 3.5260812e+43 | J128: 32 | K128: CARRO PROPRIO | L128: C
A129: 101 | B129: 46239 | C129: 000020-201 | D129: DELBONI AURIEMO S.A. | E129: 63834 | F129: 172961 | G129: 1 | H129: 548.16 | I129: 3.5260812e+43 | J129: 26 | K129: RISSO | L129: C | N129: X
A130: 101 | B130: 46239 | C130: 000020-342 | D130: DASA DIAGNOSTICO | E130: 63905 | F130: 172962 | G130: 1 | H130: 233.05 | I130: 3.5260812e+43 | J130: 32 | K130: CARRO PROPRIO | L130: C
A131: 101 | B131: 46239 | C131: 000020-523 | D131: DASA | E131: 63747 | F131: 172963 | G131: 1 | H131: 4959.56 | I131: 3.5260812e+43 | J131: 32 | K131: CARRO PROPRIO | L131: C
A132: 101 | B132: 46239 | C132: 000020-523 | D132: DASA | E132: 64096 | F132: 172964 | G132: 1 | H132: 1292 | I132: 3.5260812e+43 | J132: 32 | K132: CARRO PROPRIO | L132: C
A133: 101 | B133: 46239 | C133: 000011-001 | D133: BENEFICENCIA SP | E133: 62248 | F133: 172966 | G133: 1 | H133: 97.5 | I133: 3.5260812e+43 | J133: 32 | K133: CARRO PROPRIO | L133: C | N133: X
A134: 101 | B134: 46239 | C134: 000011-001 | D134: BENEFICENCIA SP | E134: 64125 | F134: 172967 | G134: 1 | H134: 9300 | I134: 3.5260812e+43 | J134: 32 | K134: CARRO PROPRIO | L134: C
A135: 101 | B135: 46239 | C135: 000011-001 | D135: BENEFICENCIA SP | E135: 64126 | F135: 172968 | G135: 1 | H135: 1286.3 | I135: 3.5260812e+43 | J135: 32 | K135: CARRO PROPRIO | L135: C | N135: X
A136: 101 | B136: 46239 | C136: 000011-001 | D136: BENEFICENCIA SP | E136: 64127 | F136: 172969 | G136: 1 | H136: 1417.5 | I136: 3.5260812e+43 | J136: 32 | K136: CARRO PROPRIO | L136: C | N136: X
A137: 101 | B137: 46239 | C137: 000011-001 | D137: BENEFICENCIA SP | E137: 64501 | F137: 172970 | G137: 1 | H137: 9193.5 | I137: 3.5260812e+43 | J137: 32 | K137: CARRO PROPRIO | L137: C | N137: X
A138: 101 | B138: 46239 | C138: 000020-006 | D138: DASA PQ DUQUE CAXIAS | E138: 63810 | F138: 172971 | G138: 1 | H138: 12182.18 | I138: 3.5260812e+43 | J138: 32 | K138: CARRO PROPRIO | L138: C
...

Sheet ROMANEIOS
A1: 11260 - | | | B1: 46174 | C1: CORREIOS | E1: CORREIO | F1: Filial | G1: Emissão | H1: Cliente - Loja | I1: Nome Fantasia | J1: Num.PV | K1: Num.NF | L1: Vl.NF | M1: Dt.Entrega
F2: 101 | G2: 46171 | H2: 000020 - 177 | I2: DASA 61.486.650/1161 | J2: 59434 | K2: 167718 | L2: 17276.16 | M2: 46175
F3: 101 | G3: 46171 | H3: 000036 - 003 | I3: HAPVIDA | L3: 11024.76

Sheet SEPARADORES
A1: Separadores
A2: BRADOCK
A3: JOÃO PAULO
A4: LEANDRO
A5: GLEICE
A6: PEDRO H.
A7: RAONI
A8: MIJOHNSON
A9: ALEX
A10: JOÃO OLIVEIRA
A11: JESSICA
A12: VANESSA
... A38: SAUDAVEL

Sheet DINÂMICA
A1: SEPARADOR | B1: DATA | C1: Contagem de NF | D1: Soma de SKU'S | E1: Soma de VOLUMES | F1: Soma de PALETES
A2: JOÃO PAULO | C2: 10 | D2: 69 | E2: 0
A3: LEANDRO | C3: 38 | D3: 131 | E3: 0
A4: RAONI | C4: 26 | D4: 52 | E4: 0
A5: (vazio) | C5: 6899 | D5: 0 | E5: 0 | F5: 0
A6: PAIVA | C6: 7 | D6: 45 | E6: 0
A7: RAPHAEL | C7: 26 | D7: 142 | E7: 0 | F7: 0
A8: IVAN | C8: 10 | D8: 10 | E8: 0
A9: MTC | C9: 1 | D9: 1
A10: CLAUDIO | B10: 46302 | C10: 2 | D10: 10
B11: 46304 | C11: 8 | D11: 17 | E11: 0
A12: CLAUDIO Total | C12: 10 | D12: 27 | E12: 0
A13: MARCOS | B13: 46302 | C13: 1 | D13: 6
B14: 46303 | C14: 4 | D14: 23 | E14: 0
B15: 46304 | C15: 1 | D15: 1 | E15: 0
A16: MARCOS Total | C16: 6 | D16: 30 | E16: 0
A17: MAURICIO | B17: 46302 | C17: 3 | D17: 47 | E17: 0
B18: 46303 | C18: 5 | D18: 77 | E18: 0
B19: 46304 | C19: 6 | D19: 18 | E19: 0
B20: 46305 | C20: 10 | D20: 46 | E20: 0
B21: 46306 | C21: 8 | D21: 5 | E21: 0
A22: MAURICIO Total | C22: 32 | D22: 193 | E22: 0
A23: ANDRE SOUZA | B23: 46302 | C23: 5 | D23: 8 | E23: 0
B24: 46303 | C24: 6 | D24: 10 | E24: 0
A25: ANDRE SOUZA Total | C25: 11 | D25: 18 | E25: 0
A26: WELINGTON | B26: 46302 | C26: 1 | D26: 41 | E26: 0
B27: 46303 | C27: 7 | D27: 29 | E27: 0
B28: 46304 | C28: 7 | D28: 23 | E28: 0
B29: 46305 | C29: 23 | D29: 31 | E29: 0
A30: WELINGTON Total | C30: 38 | D30: 124 | E30: 0
A31: MATHEUS | B31: 46302 | C31: 1 | D31: 1 | E31: 0
B32: 46304 | C32: 3 | D32: 8 | E32: 0
A33: MATHEUS Total | C33: 4 | D33: 9 | E33: 0
A34: SANDRO | B34: 46303 | C34: 2 | D34: 6 | E34: 0
B35: 46304 | C35: 4 | D35: 10 | E35: 0
A36: SANDRO Total | C36: 6 | D36: 16 | E36: 0
A37: KARINA | B37: 46303 | C37: 15 | D37: 20 | E37: 0
B38: 46304 | C38: 1 | D38: 1 | E38: 0
A39: KARINA Total | C39: 16 | D39: 21 | E39: 0
A40: JESSICA | B40: 46303 | C40: 1 | D40: 5 | E40: 0
A41: JESSICA Total | C41: 1 | D41: 5 | E41: 0
A42: ALEX | B42: 46303 | C42: 1 | D42: 6 | E42: 0
B43: 46304 | C43: 1 | D43: 32 | E43: 0
B44: 46305 | C44: 21 | D44: 19 | E44: 0
B45: 46306 | C45: 7 | D45: 29 | E45: 0
A46: ALEX Total | C46: 30 | D46: 86 | E46: 0
A47: MIJOHNSON | B47: 46304 | C47: 5 | D47: 44 | E47: 0
B48: 46305 | C48: 14 | D48: 55 | E48: 0
A49: MIJOHNSON Total | C49: 19 | D49: 99 | E49: 0
A50: JOÃO OLIVEIRA | B50: 46304 | C50: 4 | D50: 18 | E50: 0
B51: 46305 | C51: 11 | D51: 30 | E51: 0
B52: 46306 | C52: 3 | D52: 7 | E52: 0
A53: JOÃO OLIVEIRA Total | C53: 18 | D53: 55 | E53: 0
A54: GLEICE | B54: 46304 | C54: 5 | D54: 27 | E54: 0
B55: 46305 | C55: 8 | D55: 34 | E55: 0
B56: 46306 | C56: 3 | D56: 7 | E56: 0
A57: GLEICE Total | C57: 16 | D57: 68 | E57: 0
A58: MARIAH | B58: 46304 | C58: 2 | D58: 13 | E58: 0
B59: 46305 | C59: 12 | D59: 37 | E59: 0
B60: 46306 | C60: 5 | D60: 3 | E60: 0
A61: MARIAH Total | C61: 19 | D61: 53 | E61: 0
A62: Total Geral | C62: 7243 | D62: 1254 | E62: 0 | F62: 0

Sheet SKU
A1: Filial | B1: EmissÃ£o | C1: Pedido | D1: Cliente-Loja | E1: Nome Fantasia | F1: Produto | G1: DescriÃ§Ã£o | H1: Qtd.Original | I1: Qtd. | J1: R$ Vda. | K1: Classe | L1: TES | M1: Armz.
A2: 101 | B2: 46153 | C2: 58116 | D2: 000125-001 | E2: SOLUTION BELA VISTA | F2: 160001 | G2: BASE SELADORA ACRILICA SEALER 5L | H2: 4 | I2: 0 | J2: 345.86 | K2: 9003 | L2: 561 | M2: 1
A3: 101 | B3: 46153 | C3: 58116 | D3: 000125-001 | E3: SOLUTION BELA VISTA | F3: 280382 | G3: CERA FANTASTIC HIGH GLOSS 5L | H3: 4 | I3: 0 | J3: 365.4 | K3: 9003 | L3: 717 | M3: 1
A4: 101 | B4: 46181 | C4: 60105 | D4: 000024-002 | E4: ALBERT EINSTEIN | F4: 15196 | G4: AVENTAL PREMIUM COM PUNHO EM MALHA REF.1360 | H4: 35000 | I4: 0 | J4: 122850 | K4: 9003 | L4: 501 | M4: 1
A5: 101 | B5: 46195 | C5: 61413 | D5: 000007-001 | E5: AMOEDO | F5: 15400 | G5: SACO HAMPER AZUL ROLO S/ CORDAO 80X100X0.06 C/50 | H5: 1 | I5: 0 | J5: 26.24 | K5: 9003 | L5: 722 | M5: 1
A6: 101 | B6: 46206 | C6: 62288 | D6: 000011-001 | E6: BENEFICENCIA SP | F6: 14710 | G6: LUVA P/BANHO C/5 | H6: 6000 | I6: 0 | J6: 11700 | K6: 9003 | L6: 501 | M6: 1
A7: 101 | B7: 46217 | C7: 62906 | D7: 000792-001 | E7: C B C | F7: 190229 | G7: REFIL MOPINHO AZUL PONTA CORTADA 30CM | H7: 187 | I7: 2 | J7: 5095.75 | K7: 9003 | L7: 501 | M7: 1
A8: 101 | B8: 46225 | C8: 63681 | D8: 003595-001 | E8: SIDE | F8: 15420 | G8: SABAO EM PO 800G | H8: 2 | I8: 0 | J8: 38.4 | L8: 507 | M8: 1
A9: 101 | B9: 46225 | C9: 63681 | D9: 003595-001 | E9: SIDE | F9: 60007 | G9: FLANELA BRANCA 40X60CM | H9: 6 | I9: 0 | J9: 15.54 | K9: 9003 | L9: 501 | M9: 1
A10: 101 | B10: 46225 | C10: 63681 | D10: 003595-001 | E10: SIDE | F10: 60008 | G10: PANO SACO ALVEJADO 45X65 | H10: 10 | I10: 0 | J10: 47 | K10: 9003 | L10: 501 | M10: 1
A11: 101 | B11: 46225 | C11: 63681 | D11: 003595-001 | E11: SIDE | F11: 70130 | G11: LUVA TOP VERDE M | H11: 4 | I11: 0 | J11: 40.8 | K11: 9003 | L11: 802 | M11: 1
A12: 101 | B12: 46225 | C12: 63681 | D12: 003595-001 | E12: SIDE | F12: 70151 | G12: LUVA PLUS LARANJA P | H12: 2 | I12: 0 | J12: 19.8 | L12: 802 | M12: 1
A13: 101 | B13: 46225 | C13: 63681 | D13: 003595-001 | E13: SIDE | F13: 70152 | G13: LUVA PLUS LARANJA M | H13: 3 | I13: 0 | J13: 29.7 | L13: 802 | M13: 1
A14: 101 | B14: 46225 | C14: 63681 | D14: 003595-001 | E14: SIDE | F14: 70153 | G14: LUVA PLUS LARANJA G | H14: 2 | I14: 0 | J14: 19.8 | L14: 802 | M14: 1
A15: 101 | B15: 46225 | C15: 63681 | D15: 003595-001 | E15: SIDE | F15: 80119 | G15: SABAO EM PEDRA 160G GLICERINADO C/5 | H15: 6 | I15: 0 | J15: 98.82 | K15: 9003 | L15: 501 | M15: 1
A16: 101 | B16: 46225 | C16: 63681 | D16: 003595-001 | E16: SIDE | F16: 80358 | G16: DETERGENTE AGIPRO CLEENE 5L | H16: 1 | I16: 0 | J16: 33.83 | K16: 9003 | L16: 507 | M16: 1
A17: 101 | B17: 46225 | C17: 63681 | D17: 003595-001 | E17: SIDE | F17: 160039 | G17: MULTIUSO STAR GLASS 5L | H17: 2 | I17: 0 | J17: 97 | K17: 9003 | L17: 507 | M17: 1
A18: 101 | B18: 46225 | C18: 63681 | D18: 003595-001 | E18: SIDE | F18: 160049 | G18: DESENGRAXANTE CLEAN GREASE 5L | H18: 2 | I18: 0 | J18: 150 | K18: 9003 | L18: 507 | M18: 1
A19: 101 | B19: 46225 | C19: 63681 | D19: 003595-001 | E19: SIDE | F19: 160054 | G19: DESINFETANTE ALGAS MARINHAS VERSATIL 5L | H19: 1 | I19: 0 | J19: 34.88 | K19: 9003 | L19: 501 | M19: 1
A20: 101 | B20: 46225 | C20: 63681 | D20: 003595-001 | E20: SIDE | F20: 170106 | G20: ESPONJA SB NAO RISCA AZUL SCOTCH | H20: 15 | I20: 0 | J20: 46.5 | K20: 9003 | L20: 507 | M20: 1
A21: 101 | B21: 46225 | C21: 63681 | D21: 003595-001 | E21: SIDE | F21: 260021 | G21: HIPOCLORITO 5% BUTTERFLY 5L | H21: 1 | I21: 0 | J21: 23.48 | K21: 9003 | L21: 501 | M21: 1
A22: 101 | B22: 46225 | C22: 63681 | D22: 003595-001 | E22: SIDE | F22: 280707 | G22: PULVERIZADOR 500ML PERSONALIZADO MULTIUSO | H22: 2 | I22: 0 | J22: 12.1 | K22: 9003 | L22: 501 | M22: 1
A23: 101 | B23: 46225 | C23: 63681 | D23: 003595-001 | E23: SIDE | F23: 280710 | G23: PULVERIZADOR 500ML PERSONALIZADO DESINFETANTE | H23: 2 | I23: 0 | J23: 12.1 | K23: 9003 | L23: 501 | M23: 1
A24: 101 | B24: 46225 | C24: 63717 | D24: 000003-023 | E24: AFIP | F24: 15744 | G24: ENV PLAST PELBD TRANSP IMP ESPECIMES | H24: 20000 | I24: 0 | J24: 16400 | K24: 9003 | L24: 501 | M24: 1
A25: 101 | B25: 46227 | C25: 63892 | D25: 000024-003 | E25: ALBERT EINSTEIN | F25: 170064 | G25: FIBRA DE LIMPEZA PESADA VERDE 102X230 | H25: 100 | I25: 0 | J25: 314 | K25: 9003 | L25: 501 | M25: 1
A26: 101 | B26: 46232 | C26: 64084 | D26: 000064-002 | E26: SECONCI MATARAZZO | F26: 170067 | G26: DISCO LIMPADOR VERDE 410MM | H26: 3 | I26: 0 | J26: 93.36 | K26: 9003 | L26: 501 | M26: 1
A27: 101 | B27: 46238 | C27: 64354 | D27: 000001-001 | E27: MASTER HIGIMED SP | F27: 80201 | G27: ODORIZADOR TALCO 360ML | H27: 2 | I27: 0 | J27: 26.86 | L27: 682 | M27: 1
A28: 101 | B28: 46239 | C28: 64514 | D28: 000894-001 | E28: HOSP SAO VICENTE | F28: 120238 | G28: DISPENSER AUTO CORTE FUME 23CM ELISA | H28: 10 | I28: 0 | J28: 2328.4 | K28: 9003 | L28: 909 | M28: 1
A29: 101 | B29: 46240 | C29: 64673 | D29: 002422-002 | E29: GUIMA CONSECO | F29: 170009 | G29: FLEX LIMPA BANHEIROS 4B | H29: 3 | I29: 0 | J29: 1526.04 | K29: 9003 | L29: 501 | M29: 1
A30: 101 | B30: 46241 | C30: 64819 | D30: 000043-007 | E30: LIDERANCA DF | F30: 10016 | G30: ALCOOL 70 1L | H30: 1 | I30: 1 | J30: 7.25 | K30: 9003 | L30: 501 | M30: 1
A31: 101 | B31: 46241 | C31: 64819 | D31: 000043-007 | E31: LIDERANCA DF | F31: 30220 | G31: SACO P/ LIXO PRETO 60L 60X70 LEVE | H31: 2 | I31: 2 | J31: 32.5 | K31: 9003 | L31: 501 | M31: 1
A32: 101 | B32: 46241 | C32: 64819 | D32: 000043-007 | E32: LIDERANCA DF | F32: 60001 | G32: PANO SACO ALVEJADO G 40X65 | H32: 3 | I32: 3 | J32: 7.95 | K32: 9003 | L32: 501 | M32: 1
A33: 101 | B33: 46241 | C33: 64819 | D33: 000043-007 | E33: LIDERANCA DF | F33: 60007 | G33: FLANELA BRANCA 40X60CM | H33: 3 | I33: 3 | J33: 4.47 | K33: 9003 | L33: 501 | M33: 1
A34: 101 | B34: 46241 | C34: 64819 | D34: 000043-007 | E34: LIDERANCA DF | F34: 70067 | G34: LUVA SOFT VERDE M | H34: 1 | I34: 1 | J34: 5.6 | K34: 9003 | L34: 802 | M34: 1
A35: 101 | B35: 46241 | C35: 64819 | D35: 000043-007 | E35: LIDERANCA DF | F35: 70126 | G35: LUVA TOP AMARELA M | H35: 1 | I35: 1 | J35: 5.6 | K35: 9003 | L35: 802 | M35: 1
A36: 101 | B36: 46241 | C36: 64819 | D36: 000043-007 | E36: LIDERANCA DF | F36: 130008 | G36: TOUCA BRANCA SANFONADA C/ 100 | H36: 1 | I36: 1 | J36: 11.02 | K36: 9003 | L36: 501 | M36: 1
A37: 101 | B37: 46241 | C37: 64819 | D37: 000043-007 | E37: LIDERANCA DF | F37: 160005 | G37: DETERGENTE BECKPLATER CONCENTO 5L | H37: 1 | I37: 1 | J37: 38.73 | K37: 9003 | L37: 501 | M37: 1
A38: 101 | B38: 46241 | C38: 64819 | D38: 000043-007 | E38: LIDERANCA DF | F38: 160048 | G38: CLOREX USO HOSPITALAR 5L | H38: 1 | I38: 1 | J38: 29.43 | K38: 9003 | L38: 501 | M38: 1
A39: 101 | B39: 46241 | C39: 64819 | D39: 000043-007 | E39: LIDERANCA DF | F39: 170028 | G39: FIBRA DE LIMPEZA GERAL VERDE 102X230 | H39: 3 | I39: 3 | J39: 3.63 | K39: 9003 | L39: 501 | M39: 1
A40: 101 | B40: 46241 | C40: 64819 | D40: 000043-007 | E40: LIDERANCA DF | F40: 170052 | G40: DISCO LIMPADOR VERDE 440MM | H40: 1 | I40: 1 | J40: 21.75 | L40: 501 | M40: 1
A41: 101 | B41: 46241 | C41: 64819 | D41: 000043-007 | E41: LIDERANCA DF | F41: 250010 | G41: ALCOOL GEL MULTI SEPT REFIL 800ML | H41: 1 | I41: 1 | J41: 12.55 | K41: 9003 | L41: 501 | M41: 1
A42: 101 | B42: 46241 | C42: 64819 | D42: 000043-007 | E42: LIDERANCA DF | F42: 280237 | G42: PAPEL HIGIENICO FOLHA SIMPLES BRANCO FARDO C\ 16X4X30M | H42: 1 | I42: 1 | J42: 64.84 | K42: 9003 | L42: 802 | M42: 1
A43: 101 | B43: 46241 | C43: 64819 | D43: 000043-007 | E43: LIDERANCA DF | F43: 390511 | G43: PAPEL TOALHA FOLHA SIMPLES 2D 100% 20X21 | H43: 13 | I43: 13 | J43: 187.46 | K43: 9003 | L43: 501 | M43: 1
A44: 101 | B44: 46244 | C44: 64885 | D44: 000003-020 | E44: AFIP | F44: 15261 | G44: ENV PLAST PELBD TRANSP TEMP AMBIENTE BRASIL APOIO | H44: 17800 | I44: 0 | J44: 12104 | K44: 9003 | L44: 501 | M44: 1
A45: 101 | B45: 46244 | C45: 64892 | D45: 000020-371 | E45: DASA DIAGNOSTICO | F45: 14837 | G45: PAPEL TOALHA INTERFOLHADO FOLHA SIMPLES 2D 20X21 C/5000 | H45: 4 | I45: 3 | J45: 325.8 | K45: 9003 | L45: 501 | M45: 1
A46: 101 | B46: 46245 | C46: 65033 | D46: 000020-581 | E46: DASA IMPAR | F46: 15084 | G46: SACO P/ LIXO PRETO 20L 50X50 P-25 | H46: 15 | I46: 0 | J46: 170.55 | K46: 9003 | L46: 501 | M46: 1
A47: 101 | B47: 46245 | C47: 65033 | D47: 000020-581 | E47: DASA IMPAR | F47: 15408 | G47: PAPEL HIGIENICO ROLAO 100% 8X300 | H47: 40 | I47: 0 | J47: 1907.2 | K47: 9003 | L47: 802 | M47: 1
A48: 101 | B48: 46245 | C48: 65033 | D48: 000020-581 | E48: DASA IMPAR | F48: 20132 | G48: PAPEL TOALHA BOBINA 6X20X200 | H48: 40 | I48: 0 | J48: 3676.8 | K48: 9003 | L48: 501 | M48: 1
A49: 101 | B49: 46245 | C49: 65033 | D49: 000020-581 | E49: DASA IMPAR | F49: 250061 | G49: SABONETE ESPUMA PLUS ERVA DOCE 800ML P/VALV FIXA | H49: 20 | I49: 0 | J49: 316.6 | K49: 9003 | L49: 501 | M49: 1
A50: 101 | B50: 46245 | C50: 65033 | D50: 000020-581 | E50: DASA IMPAR | F50: 280243 | G50: SACO P/ LIXO PRETO 100L 75X90 (INO) | H50: 14 | I50: 0 | J50: 509.74 | K50: 9003 | L50: 501 | M50: 1
A51: 101 | B51: 46245 | C51: 65033 | D51: 000020-581 | E51: DASA IMPAR | F51: 399998 | G51: PAPEL TOALHA INTERFOLHADO FD 2D MH 22.5 X 21 C/2000 | H51: 40 | I51: 0 | J51: 3393.2 | K51: 9003 | L51: 501 | M51: 1
A52: 101 | B52: 46245 | C52: 65062 | D52: 000024-002 | E52: ALBERT EINSTEIN | F52: 30070 | G52: SACOLA PLASTICA BRANCA C/ TALA 25X40 C/ LOGOMARCA EINSTEIN | H52: 1000 | I52: 0 | J52: 1770 | K52: 9003 | L52: 501 | M52: 1
... A80: 101 | B80: 46254 | C80: 66211 | D80: 000024-003 | E80: ALBERT EINSTEIN | F80: 15568 | G80: SACO P/ LIXO HAMPER VERMELHO ROLO 75X90 C/ FITILHO C/ 50 | H80: 18 | I80: 0 | J80: 697.5 | K80: 9003 | L80: 501 | M80: 1
A81: 101 | B81: 46254 | C81: 66212 | D81: 000024-003 | E81: ALBERT EINSTEIN | F81: 30304 | G81: SACO HAMPER VERMELHO 80X90X0,05 C/ FITILHO C/50 | H81: 82 | I81: 0 | J81: 3177.5 | L81: 501 | M81: 1
A82: 101 | B82: 46254 | C82: 66223 | D82: 000049-001 | E82: HOSPITAL MORIAH 19.0 | F82: 15533 | G82: SACO PLASTICO CRISTAL 20X30X0,05 C/ABA HOT MELT C/100 | H82: 40 | I82: 0 | J82: 907.2 | K82: 9003 | L82: 501 | M82: 1
A83: 101 | B83: 46255 | C83: 66258 | D83: 001240-008 | E83: HOSPITAL SIRIO | F83: 15944 | G83: SACO PLASTICO TRANSP S/ PERSONALIZACAO 15X20CM 0,10MM C/ 1000 UNI | H83: 20 | I83: 7 | J83: 21338.4 | K83: 9003 | L83: 501 | M83: 1
A84: 101 | B84: 46255 | C84: 66312 | D84: 000003-019 | E84: AFIP CAC GUARULHOS | F84: 15797 | G84: ENV PELB ANATOMIA PATOLOGICA | H84: 9800 | I84: 0 | J84: 6664 | K84: 9003 | L84: 507 | M84: 1
A85: 101 | B85: 46258 | C85: 66362 | D85: 003049-002 | E85: HARM | F85: 30316 | G85: SACO P/ LIXO PRETO 100L PRIME 75X80 P-20 C/ 100 | H85: 20 | I85: 0 | J85: 440 | K85: 9003 | L85: 501 | M85: 1
A86: 101 | B86: 46258 | C86: 66384 | D86: 000020-119 | E86: DASA BELA VISTA | F86: 400000 | G86: AGUA DE COCO 200 ML C/27 | H86: 10 | I86: 5 | J86: 873.1 | K86: 9003 | L86: 501 | M86: 1
A87: 101 | B87: 46259 | C87: 66419 | D87: 003430-002 | E87: CACAU SHOW | F87: 280759 | G87: PROTETOR DE BARBA / BIGODE TNT BRANCO C/100 | H87: 8 | I87: 1 | J87: 135.2 | K87: 9003 | L87: 501 | M87: 1
A88: 101 | B88: 46260 | C88: 66483 | D88: 000003-002 | E88: AFIP SANTANA | F88: 15797 | G88: ENV PELB ANATOMIA PATOLOGICA | H88: 10000 | I88: 0 | J88: 6800 | K88: 9003 | L88: 501 | M88: 1
A89: 101 | B89: 46262 | C89: 66647 | D89: 000024-003 | E89: ALBERT EINSTEIN | F89: 30304 | G89: SACO HAMPER VERMELHO 80X90X0,05 C/ FITILHO C/50 | H89: 10 | I89: 0 | J89: 387.5 | L89: 501 | M89: 1
A90: 101 | B90: 46262 | C90: 66649 | D90: 000024-003 | E90: ALBERT EINSTEIN | F90: 30304 | G90: SACO HAMPER VERMELHO 80X90X0,05 C/ FITILHO C/50 | H90: 5 | I90: 0 | J90: 193.75 | L90: 501 | M90: 1
A91: 101 | B91: 46262 | C91: 66692 | D91: 000003-023 | E91: AFIP | F91: 12322 | G91: SCALP DESCARTAVEL C/ DISPOSITIVO DE SEGURANCA 21G | H91: 300 | I91: 0 | J91: 156 | K91: 9003 | L91: 802 | M91: 1
A92: 101 | B92: 46262 | C92: 66692 | D92: 000003-023 | E92: AFIP | F92: 12323 | G92: SCALP DESCARTAVEL C/ DISPOSITIVO DE SEGURANCA 23G | H92: 210 | I92: 0 | J92: 109.2 | K92: 9003 | L92: 802 | M92: 1
A93: 101 | B93: 46262 | C93: 66692 | D93: 000003-023 | E93: AFIP | F93: 150376 | G93: SERINGA DESCARTAVEL S/ AGULHA SLIP 10ML | H93: 600 | I93: 0 | J93: 408 | K93: 9003 | L93: 802 | M93: 1
A94: 101 | B94: 46262 | C94: 66709 | D94: 000024-003 | E94: ALBERT EINSTEIN | F94: 30304 | G94: SACO HAMPER VERMELHO 80X90X0,05 C/ FITILHO C/50 | H94: 100 | I94: 0 | J94: 3875 | L94: 501 | M94: 1
A95: 101 | B95: 46263 | C95: 66722 | D95: 000024-003 | E95: ALBERT EINSTEIN | F95: 30304 | G95: SACO HAMPER VERMELHO 80X90X0,05 C/ FITILHO C/50 | H95: 6 | I95: 0 | J95: 232.5 | L95: 501 | M95: 1
A96: 101 | B96: 46263 | C96: 66736 | D96: 000024-021 | E96: ALBERT EINSTEIN | F96: 130012 | G96: AVENTAL S/ MANG AZUL MARINHO GG 50 GR C/10 REF.1545 | H96: 46 | I96: 0 | J96: 1559.4 | K96: 9003 | L96: 501 | M96: 1
A97: 101 | B97: 46263 | C97: 66744 | D97: 000024-002 | E97: ALBERT EINSTEIN | F97: 130012 | G97: AVENTAL S/ MANG AZUL MARINHO GG 50 GR C/10 REF.1545 | H97: 202 | I97: 0 | J97: 6847.8 | K97: 9003 | L97: 501 | M97: 1
A98: 101 | B98: 46263 | C98: 66744 | D98: 000024-002 | E98: ALBERT EINSTEIN | F98: 280107 | G98: AVENTAL GOLA PADRE BRANCO 140X120 C/BOTAO C/10 (GT) | H98: 90 | I98: 0 | J98: 6040.8 | K98: 9003 | L98: 501 | M98: 1
A99: 101 | B99: 46263 | C99: 66744 | D99: 000024-002 | E99: ALBERT EINSTEIN | F99: 280137 | G99: GORRO DESCARTAVEL AZUL C/ 100 (DT) | H99: 60 | I99: 0 | J99: 6762 | K99: 9003 | L99: 501 | M99: 1
A100: 101 | B100: 46263 | C100: 66745 | D100: 000024-002 | E100: ALBERT EINSTEIN | F100: 15482 | G100: TOUCA DESCARTAVEL AFRO 70X70 BRANCA C/50 | H100: 100 | I100: 0 | J100: 5419 | K100: 9003 | L100: 501 | M100: 1
A101: 101 | B101: 46263 | C101: 66745 | D101: 000024-002 | E101: ALBERT EINSTEIN | F101: 15539 | G101: SAPATILHA PROPE DESCARTAVEL AZUL 30G C/100 | H101: 3 | I101: 0 | J101: 49.92 | K101: 9003 | L101: 501 | M101: 1
A102: 101 | B102: 46265 | C102: 66760 | D102: 000024-003 | E102: ALBERT EINSTEIN | F102: 280694 | G102: SACO HAMPER MARROM C/ FITILHO 80X90X0.05 C/50 | H102: 90 | I102: 0 | J102: 3487.5 | K102: 9003 | L102: 501 | M102: 1
A103: 101 | B103: 46265 | C103: 66762 | D103: 000024-003 | E103: ALBERT EINSTEIN | F103: 30304 | G103: SACO HAMPER VERMELHO 80X90X0,05 C/ FITILHO C/50 | H103: 20 | I103: 0 | J103: 775 | L103: 501 | M103: 1
A104: 101 | B104: 46265 | C104: 66810 | D104: 000020-177 | E104: DASA 61.486.650/1161 | F104: 280638 | G104: SAPATILHA PROPE DESCARTAVEL BRANCO C/100 | H104: 9 | I104: 9 | J104: 136.71 | K104: 9003 | L104: 501 | M104: 1
A105: 101 | B105: 46266 | C105: 66876 | D105: 003049-003 | E105: CSSM | F105: 30046 | G105: SACO INFECTANTE 100L 75X105X0.2 | H105: 69 | I105: 0 | J105: 2822.1 | K105: 9003 | L105: 501 | M105: 1
A106: 101 | B106: 46267 | C106: 66940 | D106: 001281-001 | E106: IGESP 61.442.190/000 | F106: 280701 | G106: PANO MULTIUSO AZUL 28X25 C/ 50 | H106: 80 | I106: 25 | J106: 640 | K106: 9003 | L106: 501 | M106: 1
A107: 101 | B107: 46267 | C107: 66981 | D107: 000792-001 | E107: C B C | F107: 190406 | G107: CABO P/ MOPINHO 1.20X24MM FOSCO AZUL | H107: 11 | I107: 0 | J107: 295.9 | K107: 9003 | L107: 501 | M107: 1
A108: 101 | B108: 46267 | C108: 67000 | D108: 000062-003 | E108: HOSP SANTA JOANA | F108: 30250 | G108: SACO P/ LIXO AZUL 40L LEVE | H108: 88 | I108: 0 | J108: 501.6 | K108: 9003 | L108: 501 | M108: 1
A109: 101 | B109: 46267 | C109: 67001 | D109: 000064-001 | E109: SECONCI HELIOPOLIS | F109: 170071 | G109: DISCO REMOVEDOR PRETO 350MM | H109: 11 | I109: 0 | J109: 199.1 | K109: 9003 | L109: 501 | M109: 1
A110: 101 | B110: 46268 | C110: 67069 | D110: 000036-003 | E110: HAPVIDA | F110: 60043 | G110: PANO MULTIUSO BRANCO 28X300M | H110: 100 | I110: 0 | J110: 7100 | K110: 9003 | L110: 501 | M110: 1
A111: 101 | B111: 46268 | C111: 67088 | D111: 000036-095 | E111: HAPVIDA | F111: 15408 | G111: PAPEL HIGIENICO ROLAO 100% 8X300 | H111: 10 | I111: 0 | J111: 464 | K111: 9003 | L111: 802 | M111: 1
A112: 101 | B112: 46268 | C112: 67088 | D112: 000036-095 | E112: HAPVIDA | F112: 15715 | G112: SACO P/ LIXO TOXICO LARANJA 110L 75X105X0.55 SUPER REFORCADO C/ 100 | H112: 1 | I112: 0 | J112: 80.5 | K112: 9003 | L112: 501 | M112: 1
A113: 101 | B113: 46268 | C113: 67088 | D113: 000036-095 | E113: HAPVIDA | F113: 20132 | G113: PAPEL TOALHA BOBINA 6X20X200 | H113: 10 | I113: 0 | J113: 814.8 | K113: 9003 | L113: 501 | M113: 1
A114: 101 | B114: 46268 | C114: 67088 | D114: 000036-095 | E114: HAPVIDA | F114: 30006 | G114: SACO INFECTANTE 30L 59X62X0,2 | H114: 4 | I114: 0 | J114: 72 | K114: 9003 | L114: 501 | M114: 1
A115: 101 | B115: 46268 | C115: 67088 | D115: 000036-095 | E115: HAPVIDA | F115: 30315 | G115: SACO P/ LIXO PRETO 60L PRIME 55X65 P-20 C/ 100 | H115: 5 | I115: 0 | J115: 65 | K115: 9003 | L115: 501 | M115: 1
... A222: 101 | B222: 46268 | C222: 67116 | D222: 000036-034 | E222: HAPVIDA | F222: 150106 | G222: MASCARA LARINGEA RETA DESCAR N3 | H222: 2 | I222: 0 | J222: 126.32 | K222: 9003 | L222: 802 | M222: 1
A223: 101 | B223: 46268 | C223: 67116 | D223: 000036-034 | E223: HAPVIDA | F223: 150381 | G223: BANDAGEM BLOOD STOP POS COLETA C/ 500 | H223: 1 | I223: 0 | J223: 18.5 | L223: 501 | M223: 1
A224: 101 | B224: 46268 | C224: 67116 | D224: 000036-034 | E224: HAPVIDA | F224: 270016 | G224: RIBBON CERA 110MMX74MTS | H224: 30 | I224: 0 | J224: 278.4 | K224: 9003 | L224: 501 | M224: 1
A225: 101 | B225: 46268 | C225: 67116 | D225: 000036-034 | E225: HAPVIDA | F225: 280443 | G225: COLETOR PERFURO CORTANTE 13L ECOLOGIC AMARELO | H225: 40 | I225: 0 | J225: 212 | K225: 9003 | L225: 501 | M225: 1
A226: 101 | B226: 46268 | C226: 67116 | D226: 000036-034 | E226: HAPVIDA | F226: 280499 | G226: TIRA GRUDE 40ML | H226: 2 | I226: 0 | J226: 30.18 | K226: 9003 | L226: 501 | M226: 1
A227: 101 | B227: 46268 | C227: 67116 | D227: 000036-034 | E227: HAPVIDA | F227: 280637 | G227: COPO DESCARTAVEL PLASTICO PS BRANCO 180 ML PACOTE C/ 100 | H227: 297 | I227: 0 | J227: 935.55 | K227: 9010 | L227: 501 | M227: 1
A228: 101 | B228: 46268 | C228: 67116 | D228: 000036-034 | E228: HAPVIDA | F228: 390019 | G228: LACRES P/ MALOTE 16CM LARANJA C/100 | H228: 4 | I228: 0 | J228: 36 | L228: 501 | M228: 1
A229: 101 | B229: 46268 | C229: 67116 | D229: 000036-034 | E229: HAPVIDA | F229: 390269 | G229: MASCARA DESCARTAVEL TRIPLA C/ ELASTICO C/50 | H229: 8 | I229: 0 | J229: 25.92 | K229: 9003 | L229: 501 | M229: 1
A230: 101 | B230: 46268 | C230: 67116 | D230: 000036-034 | E230: HAPVIDA | F230: 390605 | G230: CANETA ESFEROGRAFICA PRETA | H230: 50 | I230: 0 | J230: 32 | K230: 9003 | L230: 501 | M230: 1
A231: 101 | B231: 46269 | C231: 67168 | D231: 000020-058 | E231: DASA RECIFE 61.486.6 | F231: 10016 | G231: ALCOOL 70 1L | H231: 48 | I231: 0 | J231: 360.48 | K231: 9003 | L231: 501 | M231: 1
A232: 101 | B232: 46269 | C232: 67168 | D232: 000020-058 | E232: DASA RECIFE 61.486.6 | F232: 30065 | G232: BOBINA PICOTADA 25X35X0,025 C/500 | H232: 37 | I232: 0 | J232: 1602.47 | K232: 9003 | L232: 501 | M232: 1
A233: 101 | B233: 46269 | C233: 67168 | D233: 000020-058 | E233: DASA RECIFE 61.486.6 | F233: 30415 | G233: SACOLA BRANCA 40X50 C/ 100 | H233: 7 | I233: 0 | J233: 43.4 | K233: 9003 | L233: 501 | M233: 1
...

Sheet Transportes
A2: TJB
A3: BTA
A4: RISSO
A5: LEOFRAN
A6: ARLETE
A7: PACIFICO
A8: BROS
A9: RIO VERMELHO
A10: SCHREIBERLOG
A11: CARRO PROPRIO
A12: RETIRA
A13: TECNICA
... A17: CORREIOS

Sheet MOTIVOS ERROS
A1: Motivos
A2: Divergência materiais
A3: Divergência quantidades
A4: Divergência de materiais e quantidade
A6: PAULO
A7: SANDRO
A8: LEANDRO
A9: RAONI
A10: HIGOR
A11: PEDRO HENRIQUE
A12: ROBSON
A13: DAVID
... A17: RAPHAEL
A19: 1
A20: 2
A21: 3
F22: CLIENTE
A23: DIVERGÊNCIA NF X OC CLIENTE | F23: COMERCIAL
A24: DIVERGÊNCIA DE MAT. | F24: LOGISTICA
A25: DIVERGÊNCIA DE QTD. | F25: TRANSPORTADORA
A26: DIVERGENCIA DE MAT. E QTD
A27: FORA DA DATA PROGRAMADA (ANTECIPADO)
A28: FORA DA DATA PROGRAMADA (ATRASO)
A29: FALTA DE AGENDAMENTO
A30: MATERIAIS AVARIADOS
A31: REGULARIZAÇÃO TJ
A32: ENDEREÇO NÃO LOCALIZADO
A33: ENDEREÇO INCORRETO
A34: FORA DO HORARIO DE RECEBIMENTO
A35: FORA DO HORARIO DE RECEBIMENTO (DESTACADO EM NF)
A36: DUPLICIDADE
A37: MATERIAIS VENCIDOS
... A79: AGUARDANDO CONFERÊNCIA

Sheet MATERIAIS
A1: CODIGO | B1: DESCRIÇÃO | C1: MARCA
A2: 10009 | B2: DESINFETANTE EUCALIPTO 5L | C2: DVISAO
A3: 10009 | B3: DESINFETANTE EUCALIPTO 5L | C3: DVISAO
A4: 10009 | B4: DESINFETANTE EUCALIPTO 5L | C4: DVISAO
A5: 10009 | B5: DESINFETANTE EUCALIPTO 5L | C5: DVISAO
A6: 10010 | B6: DESINFETANTE LAVANDA 5L | C6: DVISAO
A7: 10010 | B7: DESINFETANTE LAVANDA 5L | C7: DVISAO
A8: 10010 | B8: DESINFETANTE LAVANDA 5L | C8: DVISAO
A9: 10010 | B9: DESINFETANTE LAVANDA 5L | C9: DVISAO
A10: 10011 | B10: DETERGENTE NEUTRO 5L | C10: DVISAO
A11: 10011 | B11: DETERGENTE NEUTRO 5L | C11: DVISAO
A12: 10011 | B12: DETERGENTE NEUTRO 5L PP&CIA | C12: HARMONIEX
A13: 10011 | B13: DETERGENTE NEUTRO 5L | C13: DVISAO
A14: 10012 | B14: HIPOCLORITO 2.5% 5L | C14: CORDEX
A15: 10013 | B15: PANO MICROFIBRA 80X60 - LARANJA
A16: 10014 | B16: ALCOOL 99 1L | C16: SANTA CRUZ
A17: 10014 | B17: ALCOOL 99 1L | C17: SANTA CRUZ
A18: 10014 | B18: ALCOOL 99 1L | C18: SANTA CRUZ
A19: 10014 | B19: ALCOOL 99 1L | C19: SANTA CRUZ
A20: 10018 | B20: ALCOOL 70 100ML | C20: RICIE
A21: 10018 | B21: ALCOOL 70 100ML | C21: RICIE
A22: 10018 | B22: ALCOOL 70 100ML | C22: RICIE
A23: 10018 | B23: ALCOOL 70 100ML | C23: RICIE
A24: 10018 | B24: ALCOOL 70 100ML | C24: RICIE
A25: 10018 | B25: ALCOOL 70 100ML | C25: RICIE
A26: 10018 | B26: ALCOOL 70 100ML | C26: RICIE
A27: 10018 | B27: ALCOOL 70 100ML | C27: RICIE
... A31: 10024 | B31: AROMATIZANTE FLORAL 5L | C31: CORDEX
A32: 10034 | B32: ESSENCIA DE EUCALIPTO 1000ML
A33: 10034 | B33: ESSENCIA DE EUCALIPTO 1000ML
A34: 10059 | B34: ALCOOL GEL 70 500ML | C34: SANTA CRUZ
A35: 10059 | B35: ALCOOL GEL 70 500ML | C35: SANTA CRUZ
A36: 10059 | B36: ALCOOL GEL 70 500ML | C36: SANTA CRUZ
A37: 10060 | B37: ALCOOL GEL 70 500ML | C37: SAFRA
A38: 10063 | B38: HIPOCLORITO 12% 5L | C38: CORDEX
A39: 10064 | B39: POLIDOR METAL BRASS POLISH 1L | C39: SPARTAN
A40: 10064 | B40: POLIDOR METAL BRASS POLISH 1L | C40: SPARTAN
A41: 10064 | B41: POLIDOR METAL BRASS POLISH 1L | C41: SPARTAN
A42: 10064 | B42: POLIDOR METAL BRASS POLISH 1L | C42: SPARTAN
A43: 10077 | B43: SABONETE ESPUMA NEUTRO 400ML | C43: MASTER HIGIMED
A44: 10077 | B44: SABONETE ESPUMA NEUTRO 400ML | C44: MASTER HIGIMED
A45: 10077 | B45: SABONETE ESPUMA NEUTRO 400ML | C45: MASTER HIGIMED
... A61: 10091 | B61: HIPOCLORITO 1% 5L | C61: DVISAO
A62: 10094 | B62: HIPOCLORITO 1% 2L
A63: 10094 | B63: HIPOCLORITO 1% 2L | C63: DVISAO
A64: 10095 | B64: LIMPA ALUMINIO 5L | C64: DVISAO
A65: 10095 | B65: LIMPA ALUMINIO 5L | C65: DVISAO
A66: 10095 | B66: LIMPA ALUMINIO 5L | C66: DVISAO
A67: 10095 | B67: LIMPA ALUMINIO 5L | C67: DVISAO
A68: 10098 | B68: ALCOOL 46 1L | C68: SANTA CRUZ
A69: 10098 | B69: ALCOOL 46 1L | C69: SANTA CRUZ
A70: 10104 | B70: HIPOCLORITO 12% 5L | C70: DVISAO
A71: 10104 | B71: HIPOCLORITO 12% 5L | C71: DVISAO
A72: 10104 | B72: HIPOCLORITO 12% 5L | C72: DVISAO
A73: 10104 | B73: HIPOCLORITO 12% 5L | C73: DVISAO
A74: 10106 | B74: ALCOOL GEL REFIL 1000ML | C74: MASTER HIGIMED
A75: 10106 | B75: ALCOOL GEL REFIL 1000ML
A76: 10109 | B76: SABONETE ESPUMA COTTON REFIL 400ML | C76: MASTER HIGIMED
A77: 10109 | B77: SABONETE ESPUMA COTTON REFIL 400ML
A78: 10118 | B78: DETERGENTE DESENGRAXANTE CHEFF ROYAL 5L | C78: ROYAL QUALITY
A79: 10118 | B79: DETERGENTE DESENGRAXANTE CHEFF ROYAL 5L | C79: ROYAL QUALITY
A80: 10118 | B80: DETERGENTE DESENGRAXANTE CHEFF ROYAL 5L | C80: ROYAL QUALITY
A81: 10118 | B81: DETERGENTE DESENGRAXANTE CHEFF ROYAL 5L | C81: ROYAL QUALITY
A82: 10120 | B82: ALCOOL SAFRA GEL 70 INPM BACTERICIDA 5 LITROS | C82: SAFRA
A83: 10122 | B83: ESSENCIA FLORAL 140ML | C83: COALA
A84: 10126 | B84: AMACIANTE SOFT BLUE 5L | C84: DVISAO
A85: 10126 | B85: AMACIANTE SOFT BLUE 5L | C85: DVISAO
A86: 10126 | B86: AMACIANTE SOFT BLUE 5L | C86: DVISAO
A87: 10126 | B87: AMACIANTE SOFT BLUE 5L | C87: DVISAO
A88: 10135 | B88: ALCOOL ISOPROPILICO 5L
A89: 10135 | B89: ALCOOL ISOPROPILICO 5L
A90: 10144 | B90: DETERGENTE NEUTRO 5L | C90: CORDEX
A91: 10146 | B91: LIMPA VIDROS 5L
A92: 10146 | B92: LIMPA VIDROS 5L | C92: CORDEX
A93: 10148 | B93: HIPOCLORITO 10% 5L | C93: DVISAO
A94: 10148 | B94: HIPOCLORITO 10% 5L | C94: DVISAO
A95: 10148 | B95: HIPOCLORITO 10% 5L | C95: DVISAO
A96: 10148 | B96: HIPOCLORITO 10% 5L | C96: DVISAO
A97: 10153 | B97: HIPOCLORITO 2.5% 5L | C97: DVISAO
A98: 10153 | B98: HIPOCLORITO 2.5% 5L | C98: DVISAO
A99: 10153 | B99: HIPOCLORITO 2.5% 5L | C99: DVISAO
A100: 10153 | B100: HIPOCLORITO 2.5% 5L | C100: DVISAO
A101: 10157 | B101: HIPOCLORITO 5 - 5L | C101: CORDEX
A102: 10160 | B102: LIMPA ALUMINIO ALUMIL 500ML | C102: START
A103: 10162 | B103: ESSENCIA CITRONELA 120ML
A104: 10162 | B104: ESSENCIA CITRONELA 120ML | C104: COALA
A105: 10164 | B105: DETERGENTE DESENGRAXANTE YELLOW PINE 5L | C105: SPARTAN
A106: 10164 | B106: DETERGENTE DESENGRAXANTE YELLOW PINE 5L | C106: SPARTAN
A107: 10164 | B107: DETERGENTE DESENGRAXANTE YELLOW PINE 5L | C107: SPARTAN
A108: 10164 | B108: DETERGENTE DESENGRAXANTE YELLOW PINE 5L | C108: SPARTAN
A109: 10165 | B109: SABONETE ESPUMA NEUTRO 1000ML | C109: MASTER HIGIMED
A110: 10165 | B110: SABONETE ESPUMA NEUTRO 1000ML | C110: MASTER HIGIMED
A111: 10165 | B111: SABONETE ESPUMA NEUTRO 1000ML | C111: MASTER HIGIMED
A112: 10165 | B112: SABONETE ESPUMA NEUTRO 1000ML | C112: MASTER HIGIMED
A113: 10168 | B113: ALCOOL SPRAY REFIL 600ML | C113: SENSY
A114: 10168 | B114: ALCOOL SPRAY REFIL 600ML
A115: 10170 | B115: SABONETE ESPUMA HERBAL REFIL 600ML | C115: SENSY
A116: 10179 | B116: LIMPA ALUMINIO 5L
A117: 10179 | B117: LIMPA ALUMINIO 5L | C117: HARMONIEX
A118: 10182 | B118: LIMPADOR HIGIENE E LIMPEZA SANEANTE NACIONAL HARMONIEX | C118: HARMONIEX
...

Sheet DINAMICA
A1: SEPARADOR | B1: DATA | C1: Contagem de PV | D1: Soma de SKU'S
A2: ALEX | C2: 1 | D2: 3
A3: CLAUDIO | C3: 1 | D3: 2
A4: GLEICE | C4: 9 | D4: 33
A5: JESSICA | C5: 1 | D5: 10
A6: JOÃO OLIVEIRA | C6: 4 | D6: 16
A7: JOÃO PAULO | C7: 1 | D7: 4
A8: KARINA | C8: 8 | D8: 20
A9: MARIAH | C9: 12 | D9: 32
A10: MAURICIO | C10: 5 | D10: 24
A11: MIJOHNSON | C11: 1 | D11: 4
A12: RAPHAEL | C12: 6 | D12: 12
A13: MIRIÃ | C13: 9 | D13: 38
... A16: FELIPE | C16: 4 | D16: 22
A17: Total Geral | C17: 81 | D17: 291 | M17: =253-330 -> -77

Sheet GRAFICO

Sheet STATUS
A1: DATA | B1: BACKLOG | C1: SAUDAVEL | D1: MATERIAL FALTANDO | E1: NFS EMITIDAS
A2: 46302 | B2: =COUNTIFS(SEPARAÇÃO!$D:$D,A2,SEPARAÇÃO!$H:$H,"BACKLOG") -> 12 | C2: =COUNTIFS(SEPARAÇÃO!$D:$D,A2,SEPARAÇÃO!$H:$H,"saudavel") -> 18 | D2: =COUNTIFS(SEPARAÇÃO!$D:$D,A2,SEPARAÇÃO!$G:$G,"material faltando") -> 0 | E2: {=SUMPRODUCT(--(TEXT(SEPARAÇÃO!D$2:D$9975,"dd/mm/aaaa")=TEXT($A2,"dd/mm/aaaa")),--(SEPARAÇÃO!A$2:A$9975<>""))} -> 30
A3: 46303 | B3: =COUNTIFS(SEPARAÇÃO!$D:$D,A3,SEPARAÇÃO!$H:$H,"BACKLOG") -> 47 | C3: =COUNTIFS(SEPARAÇÃO!$D:$D,A3,SEPARAÇÃO!$H:$H,"saudavel") -> 40 | D3: =COUNTIFS(SEPARAÇÃO!$D:$D,A3,SEPARAÇÃO!$G:$G,"material faltando") -> 0 | E3: {=SUMPRODUCT(--(TEXT(SEPARAÇÃO!D$2:D$9975,"dd/mm/aaaa")=TEXT($A3,"dd/mm/aaaa")),--(SEPARAÇÃO!A$2:A$9975<>""))} -> 84
A4: 46304 | B4: =COUNTIFS(SEPARAÇÃO!$D:$D,A4,SEPARAÇÃO!$H:$H,"BACKLOG") -> 66 | C4: =COUNTIFS(SEPARAÇÃO!$D:$D,A4,SEPARAÇÃO!$H:$H,"saudavel") -> 6 | D4: =COUNTIFS(SEPARAÇÃO!$D:$D,A4,SEPARAÇÃO!$G:$G,"material faltando") -> 0 | E4: {=SUMPRODUCT(--(TEXT(SEPARAÇÃO!D$2:D$9975,"dd/mm/aaaa")=TEXT($A4,"dd/mm/aaaa")),--(SEPARAÇÃO!A$2:A$9975<>""))} -> 67
A5: 46305 | B5: =COUNTIFS(SEPARAÇÃO!$D:$D,A5,SEPARAÇÃO!$H:$H,"BACKLOG") -> 107 | C5: =COUNTIFS(SEPARAÇÃO!$D:$D,A5,SEPARAÇÃO!$H:$H,"saudavel") -> 7 | D5: =COUNTIFS(SEPARAÇÃO!$D:$D,A5,SEPARAÇÃO!$G:$G,"material faltando") -> 6 | E5: {=SUMPRODUCT(--(TEXT(SEPARAÇÃO!D$2:D$9975,"dd/mm/aaaa")=TEXT($A5,"dd/mm/aaaa")),--(SEPARAÇÃO!A$2:A$9975<>""))} -> 107
A6: 46306 | B6: =COUNTIFS(SEPARAÇÃO!$D:$D,A6,SEPARAÇÃO!$H:$H,"BACKLOG") -> 57 | C6: =COUNTIFS(SEPARAÇÃO!$D:$D,A6,SEPARAÇÃO!$H:$H,"saudavel") -> 7 | D6: =COUNTIFS(SEPARAÇÃO!$D:$D,A6,SEPARAÇÃO!$G:$G,"material faltando") -> 2 | E6: {=SUMPRODUCT(--(TEXT(SEPARAÇÃO!D$2:D$9975,"dd/mm/aaaa")=TEXT($A6,"dd/mm/aaaa")),--(SEPARAÇÃO!A$2:A$9975<>""))} -> 62
A7: 46307 | B7: =COUNTIFS(SEPARAÇÃO!$D:$D,A7,SEPARAÇÃO!$H:$H,"BACKLOG") -> 48 | C7: =COUNTIFS(SEPARAÇÃO!$D:$D,A7,SEPARAÇÃO!$H:$H,"saudavel") -> 25 | D7: =COUNTIFS(SEPARAÇÃO!$D:$D,A7,SEPARAÇÃO!$G:$G,"material faltando") -> 3 | E7: {=SUMPRODUCT(--(TEXT(SEPARAÇÃO!D$2:D$9975,"dd/mm/aaaa")=TEXT($A7,"dd/mm/aaaa")),--(SEPARAÇÃO!A$2:A$9975<>""))} -> 67
A8: 46308 | B8: =COUNTIFS(SEPARAÇÃO!$D:$D,A8,SEPARAÇÃO!$H:$H,"BACKLOG") -> 7 | C8: =COUNTIFS(SEPARAÇÃO!$D:$D,A8,SEPARAÇÃO!$H:$H,"saudavel") -> 89 | D8: =COUNTIFS(SEPARAÇÃO!$D:$D,A8,SEPARAÇÃO!$G:$G,"material faltando") -> 0 | E8: {=SUMPRODUCT(--(TEXT(SEPARAÇÃO!D$2:D$9975,"dd/mm/aaaa")=TEXT($A8,"dd/mm/aaaa")),--(SEPARAÇÃO!A$2:A$9975<>""))} -> 90
A9: 46309 | B9: =COUNTIFS(SEPARAÇÃO!$D:$D,A9,SEPARAÇÃO!$H:$H,"BACKLOG") -> 40 | C9: =COUNTIFS(SEPARAÇÃO!$D:$D,A9,SEPARAÇÃO!$H:$H,"saudavel") -> 22 | D9: =COUNTIFS(SEPARAÇÃO!$D:$D,A9,SEPARAÇÃO!$G:$G,"material faltando") -> 0 | E9: {=SUMPRODUCT(--(TEXT(SEPARAÇÃO!D$2:D$9975,"dd/mm/aaaa")=TEXT($A9,"dd/mm/aaaa")),--(SEPARAÇÃO!A$2:A$9975<>""))} -> 60
A10: 46310 | B10: =COUNTIFS(SEPARAÇÃO!$D:$D,A10,SEPARAÇÃO!$H:$H,"BACKLOG") -> 34 | C10: =COUNTIFS(SEPARAÇÃO!$D:$D,A10,SEPARAÇÃO!$H:$H,"saudavel") -> 47 | D10: =COUNTIFS(SEPARAÇÃO!$D:$D,A10,SEPARAÇÃO!$G:$G,"material faltando") -> 1 | E10: {=SUMPRODUCT(--(TEXT(SEPARAÇÃO!D$2:D$9975,"dd/mm/aaaa")=TEXT($A10,"dd/mm/aaaa")),--(SEPARAÇÃO!A$2:A$9975<>""))} -> 51
